<?xml version="1.0" encoding="utf-8"?>
<exams>
  <!-- XX -->
  <thisQuestion>
    <qNum>id01513:date1627453500</qNum>
    <question>&lt;strong&gt;คำสั่ง: &lt;/strong&gt;ให้ท่านเลือกคำตอบที่ถูกต้องที่สุด&lt;br /&gt; &lt;br /&gt;
ประโยคใดใช้ได้อย่างถูกต้องเหมาะสม &lt;br /&gt;
	</question>
    <choice_A>บริเวณนี้ มีประชากรอยู่แน่นหนามาก</choice_A>
    <choice_B>พอเหลียวไปเห็นคนถือปีนจ้องอยู่ สุดาก็รู้สึกเยือกเย็นจับขั้วหัวใจ</choice_B>
    <choice_C>โบราณสถานที่สำคัญทุกแห่งในประเทศควรได้รับการดูแลเสียที</choice_C>
    <choice_D>เขาสนใจในหนังสือเล่มนี้มาก เพราะมีเนื้อหาเกี่ยวกับจังหวัดของเขา</choice_D>
    <choice_E>
    </choice_E>
    <correctAns>4</correctAns>
    <!-- A=2, B=3, C=4, D=5 -->
    <explanation>&lt;strong&gt;คำสั่ง: &lt;/strong&gt;ให้ท่านเลือกคำตอบที่ถูกต้องที่สุด&lt;br /&gt; &lt;br /&gt;
ประโยคใดใช้ได้อย่างถูกต้องเหมาะสม &lt;br /&gt;&lt;br /&gt;

1. บริเวณนี้ มีประชากรอยู่แน่นหนามาก&lt;br /&gt;
2. พอเหลียวไปเห็นคนถือปีนจ้องอยู่ สุดาก็รู้สึกเยือกเย็นจับขั้วหัวใจ&lt;br /&gt;
3.โบราณสถานที่สำคัญทุกแห่งในประเทศควรได้รับการดูแลเสียที ✔&lt;br /&gt;
4. เขาสนใจในหนังสือเล่มนี้มาก เพราะมีเนื้อหาเกี่ยวกับจังหวัดของเขา&lt;br /&gt;&lt;br /&gt;

	คำอธิบาย&lt;br /&gt;&lt;br /&gt;

ข้อ 1. ใช้คำผิด แน่นหนา ต้องเป็นหนาแน่น&lt;br /&gt;
แน่นหนา - มั่นคง เช่น ใส่กุญแจแน่นหนา&lt;br /&gt;
หนาแน่น - คับคั่ง, แออัด, เช่น กรุงเทพฯ มีประชากรหนาแน่นมาก&lt;br /&gt;&lt;br /&gt;

ข้อ 2.  ใช้คำผิด เยือกเย็น ต้องเป็น เย็นเยือก&lt;br /&gt;
เยือกเย็น - มีจิตใจหนักแน่น ไม่ฉุนเฉียวโกรธง่าย เช่น สำคัญที่เป็นคนเยือกเย็น จึงจะตัดสินปัญหาได้อย่างรอบคอบ&lt;br /&gt;
เย็นเยือก -อาการที่รู้สึกหนาวสะท้านถึงขั้วหัวใจ เช่น บนยอดดอยน้ำค้างตกเย็นเยือก&lt;br /&gt;&lt;br /&gt;

ข้อ 3 ถูกต้องแล้ว&lt;br /&gt;&lt;br /&gt;

ข้อ 4 ใช้ภาษาฟุ่มเฟือย - ตัดคำว่า "ใน" ออกได้ &lt;br /&gt;
เขาสนใจหนังสือเล่มนี้มาก เพราะมีเนื้อหาเกี่ยวกับจังหวัดของเขา&lt;br /&gt;&lt;br /&gt;

คำตอบที่ถูก คือ ข้อ 3 &lt;br /&gt;

	</explanation>
    <isExplain>yes</isExplain>
    <!-- ไม่แสดงป้าย คำอธิบาย ให้คลิก  - none -->
    <!-- แสดงป้าย คำอธิบาย ให้คลิก มีเฉลย+คำอธิบาย  - yes  -->
    <!-- แสดงป้าย คำอธิบาย ให้คลิก มีเฉลย+ไม่มีคำอธิบาย  - premium only  -->
    <!-- แสดงป้าย คำอธิบาย ให้คลิก ไม่เฉลย+ไม่มีคำอธิบาย  - disable answer  -->
  </thisQuestion>
  <!-- XX -->
  <thisQuestion>
    <qNum>id01514:date1627453500</qNum>
    <question>&lt;strong&gt;คำสั่ง: &lt;/strong&gt;ให้ท่านเลือกคำตอบที่ถูกต้องที่สุด&lt;br /&gt; &lt;br /&gt;
ประโยคใดใช้ได้อย่างถูกต้องเหมาะสม &lt;br /&gt;

	</question>
    <choice_A>หนูน้อยค่อย ๆ วิ่งถลาไปกอดคุณแม่</choice_A>
    <choice_B>อิเหนามีความพยายาม ที่จะลักพานางบุษบา</choice_B>
    <choice_C>เขาไปทำบุญที่วัดแล้ว มิหนำซ้ำยังได้ร่วมฟังเทศน์ด้วย</choice_C>
    <choice_D>สุนทรภู่ได้รับ พระมหากรุณาธิคุณ จากพระบาทสมเด็จ พระพุทธเลิศหล้านภาลัย</choice_D>
    <choice_E>
    </choice_E>
    <correctAns>2</correctAns>
    <!-- A=2, B=3, C=4, D=5 -->
    <explanation>&lt;strong&gt;คำสั่ง: &lt;/strong&gt;ให้ท่านเลือกคำตอบที่ถูกต้องที่สุด&lt;br /&gt; &lt;br /&gt;
ประโยคใดใช้ได้อย่างถูกต้องเหมาะสม &lt;br /&gt;
1. หนูน้อยค่อย ๆ วิ่งถลาไปกอดคุณแม่ ✔&lt;br /&gt;
2. อิเหนามีความพยายาม ที่จะลักพานางบุษบา &lt;br /&gt;
3. เขาไปทำบุญที่วัดแล้ว มิหนำซ้ำยังได้ร่วมฟังเทศน์ด้วย &lt;br /&gt;
4. สุนทรภู่ได้รับพระมหากรุณาธิคุณ จากพระบาทสมเด็จ พระพุทธเลิศหล้านภาลัย &lt;br /&gt; &lt;br /&gt;

	คำอธิบาย&lt;br /&gt;&lt;br /&gt;
ข้อ 1. ถูกต้องแล้ว &lt;br /&gt; &lt;br /&gt;

ข้อ 2. ใช้คำฟุ่มเฟือย- ตัดคำว่า "มีความ" และคำว่า "ที่" ได้ &lt;br /&gt;
อิเหนาพยายามจะลักพานางบุษบา &lt;br /&gt; &lt;br /&gt;

ข้อ 3. ใช้คำเชื่อมไม่เหมาะ ควรใช้ "และ" แทน "มิหนำซ้ำ" &lt;br /&gt; &lt;br /&gt;

ข้อ 4. ประโยคไม่สมบูรณ์ ชัดเจน คือไม่ทราบว่า ได้รับพระมหากรุณาธิคุณ ในด้านใด ให้เป็นอะไร เป็นต้น &lt;br /&gt; &lt;br /&gt;


คำตอบที่ถูก คือ ข้อ 1 &lt;br /&gt;


	</explanation>
    <isExplain>yes</isExplain>
    <!-- ไม่แสดงป้าย คำอธิบาย ให้คลิก  - none -->
    <!-- แสดงป้าย คำอธิบาย ให้คลิก มีเฉลย+คำอธิบาย  - yes  -->
    <!-- แสดงป้าย คำอธิบาย ให้คลิก มีเฉลย+ไม่มีคำอธิบาย  - premium only  -->
    <!-- แสดงป้าย คำอธิบาย ให้คลิก ไม่เฉลย+ไม่มีคำอธิบาย  - disable answer  -->
  </thisQuestion>
  <!-- XX -->
  <thisQuestion>
    <qNum>id01515:date1627453500</qNum>
    <question>&lt;strong&gt;คำสั่ง: &lt;/strong&gt;ให้ท่านเลือกคำตอบที่ถูกต้องที่สุด&lt;br /&gt; &lt;br /&gt;
ประโยคใดมีความหมายชัดเจนที่สุด &lt;br /&gt;

	</question>
    <choice_A>ฉันขายรถพี่สาว</choice_A>
    <choice_B>มานะชอบกินแกงร้อน</choice_B>
    <choice_C>เมื่อเดือนก่อนเขาทาสีบ้านที่เขาซื้อ</choice_C>
    <choice_D>เขาสนิทกับน้องสาวคุณทิพวัลย์ที่เป็นพยาบาล</choice_D>
    <choice_E>
    </choice_E>
    <correctAns>4</correctAns>
    <!-- A=2, B=3, C=4, D=5 -->
    <explanation>&lt;strong&gt;คำสั่ง: &lt;/strong&gt;ให้ท่านเลือกคำตอบที่ถูกต้องที่สุด&lt;br /&gt; &lt;br /&gt;
ประโยคใดมีความชัดเจนที่สุด &lt;br /&gt;&lt;br /&gt;

1. ฉันขายรถพี่สาว&lt;br /&gt;
2. มานะชอบกินแกงร้อน&lt;br /&gt;
3.เมื่อเดือนก่อนเขาทาสีบ้านที่เขาซื้อ ✔&lt;br /&gt;
4.เขาสนิทกับน้องสาวคุณทิพวัลย์ที่เป็นพยาบาล&lt;br /&gt;&lt;br /&gt;

	คำอธิบาย&lt;br /&gt;&lt;br /&gt;
ข้อ 1. เป็นประโยคกำกวม &lt;br /&gt;
ฉันขายรถของฉันให้แก่พี่สาว หรือ ฉันขายรถของพี่สาว (ให้คนอื่นไป) รถของฉัน หรือ รถของพี่สาว&lt;br /&gt;&lt;br /&gt;

ข้อ 2. เป็นประโยคกำกวม &lt;br /&gt;
คือ มานะชอบกินอาหารชื่อแกงร้อน หรือ มานะชอบผัดวันประกันพรุ่ง  ทำอะไรจวนตัว&lt;br /&gt;&lt;br /&gt;

ข้อ 3. ถูกต้องแล้ว&lt;br /&gt;&lt;br /&gt;

ข้อ 4. เป็นประโยคกำกวม&lt;br /&gt;
คือ ไม่ทราบว่าใครเป็นพยาบาล น้องของคุณทิพวรรณ หรือ ตัวคุณทิพวรรณเองที่เป็นพยาบาล&lt;br /&gt;&lt;br /&gt;

คำตอบที่ถูก คือ ข้อ 3 &lt;br /&gt;

	</explanation>
    <isExplain>yes</isExplain>
    <!-- ไม่แสดงป้าย คำอธิบาย ให้คลิก  - none -->
    <!-- แสดงป้าย คำอธิบาย ให้คลิก มีเฉลย+คำอธิบาย  - yes  -->
    <!-- แสดงป้าย คำอธิบาย ให้คลิก มีเฉลย+ไม่มีคำอธิบาย  - premium only  -->
    <!-- แสดงป้าย คำอธิบาย ให้คลิก ไม่เฉลย+ไม่มีคำอธิบาย  - disable answer  -->
  </thisQuestion>
  <!-- XX -->
  <thisQuestion>
    <qNum>id01516:date1627453500</qNum>
    <question>&lt;strong&gt;คำสั่ง: &lt;/strong&gt;ให้ท่านเลือกคำตอบที่ถูกต้องที่สุด&lt;br /&gt; &lt;br /&gt;
ข้อใดใช้ภาษา กำกวม &lt;br /&gt;

	</question>
    <choice_A>พี่ของน้อยที่ถูกรถชนไม่มาทำงาน</choice_A>
    <choice_B>โรคติดต่อที่เกิดจากเชื้อรารักษายาก</choice_B>
    <choice_C>รถคันที่ภารโรงขับออกไปราคาแพงมาก</choice_C>
    <choice_D>ชาวนาเข้ามาร้องทุกข์ที่หน้าทำเนียบรัฐบาล</choice_D>
    <choice_E>
    </choice_E>
    <correctAns>2</correctAns>
    <!-- A=2, B=3, C=4, D=5 -->
    <explanation>&lt;strong&gt;คำสั่ง: &lt;/strong&gt;ให้ท่านเลือกคำตอบที่ถูกต้องที่สุด&lt;br /&gt; &lt;br /&gt;
ข้อใดใช้ภาษา กำกวม &lt;br /&gt;&lt;br /&gt;

1. พี่ของน้อยที่ถูกรถชนไม่มาทำงาน ✔&lt;br /&gt;
2. โรคติดต่อที่เกิดจากเชื้อรารักษายาก&lt;br /&gt;
3. รถคันที่ภารโรงขับออกไปราคาแพงมาก&lt;br /&gt;
4. ชาวนาเข้ามาร้องทุกข์ที่หน้าทำเนียบรัฐบาล &lt;br /&gt;&lt;br /&gt;

	คำอธิบาย&lt;br /&gt;&lt;br /&gt;

ข้อ 1. ใช้ภาษากำกวม คือ ไม่รู้ว่าใครกันแน่ที่ถูกรถชน พี่ของน้อย หรือ น้อย ✔&lt;br /&gt;&lt;br /&gt;

ข้อ 2. ชัดเจน เพราะ การรักษาต้องรักษาโรค ไม่ใช่รักษาเชื้อรา เพราะ เชื้อรา ถ้าจะทำให้หมดไป ควรใช้คำว่า กำจัด เช่น กำจัดเชื้อรา&lt;br /&gt;&lt;br /&gt;

ข้อ 3. ประโยคนี้ชัดเจนว่า รถที่ขับออกไป มีราคาแพง &lt;br /&gt;&lt;br /&gt;

ข้อ 4. ประโยคนี้ ชัดเจนว่า ใคร (ชาวนา) ทำอะไร(ร้องทุกข์) ที่ไหน(หน้าทำเนียบรัฐบาล)&lt;br /&gt;&lt;br /&gt;

คำตอบที่ถูก คือ ข้อ 1 &lt;br /&gt;

	</explanation>
    <isExplain>yes</isExplain>
    <!-- ไม่แสดงป้าย คำอธิบาย ให้คลิก  - none -->
    <!-- แสดงป้าย คำอธิบาย ให้คลิก มีเฉลย+คำอธิบาย  - yes  -->
    <!-- แสดงป้าย คำอธิบาย ให้คลิก มีเฉลย+ไม่มีคำอธิบาย  - premium only  -->
    <!-- แสดงป้าย คำอธิบาย ให้คลิก ไม่เฉลย+ไม่มีคำอธิบาย  - disable answer  -->
  </thisQuestion>
  <!--  ตรวจถึงตรงนี้  -->
  <!-- XX -->
  <thisQuestion>
    <qNum>id01517:date1627453500</qNum>
    <question>&lt;strong&gt;คำสั่ง: &lt;/strong&gt;ให้ท่านเลือกคำตอบที่ถูกต้องที่สุด&lt;br /&gt; &lt;br /&gt;
ข้อใดใช้ภาษา ถูกต้องสมบูรณ์ที่สุด &lt;br /&gt;
	</question>
    <choice_A>ชีวิตของลูกผู้ชายคนหนึ่ง</choice_A>
    <choice_B>ความพยายามที่ทุกคนมีอยู่</choice_B>
    <choice_C>อุปสรรคเป็นสิ่งที่ต้องฝ่าฟัน</choice_C>
    <choice_D>ผู้สมัครสอบที่เป็นครูอัตราจ้าง</choice_D>
    <choice_E>
    </choice_E>
    <correctAns>4</correctAns>
    <!-- A=2, B=3, C=4, D=5 -->
    <explanation>&lt;strong&gt;คำสั่ง: &lt;/strong&gt;ให้ท่านเลือกคำตอบที่ถูกต้องที่สุด&lt;br /&gt; &lt;br /&gt;

ข้อใดใช้ภาษา ถูกต้องสมบูรณ์ที่สุด &lt;br /&gt;&lt;br /&gt;

1. ชีวิตของลูกผู้ชายคนหนึ่ง&lt;br /&gt;
2. ความพยายามที่ทุกคนมีอยู่&lt;br /&gt;
3. อุปสรรคเป็นสิ่งที่ต้องฝ่าฟัน ✔&lt;br /&gt;
4. ผู้สมัครสอบที่เป็นครูอัตราจ้าง&lt;br /&gt;&lt;br /&gt;

	คำอธิบาย&lt;br /&gt;&lt;br /&gt;

ข้อ 3. เป็นประโยคที่สมบูรณ์ มีครบทั้งภาคประธาน (อุปสรรค) และภาคกริยา (เป็นสิ่งที่ต้องฝ่าฟัน)&lt;br /&gt;&lt;br /&gt;

ส่วนข้ออื่น ๆ ไม่มีภาคกริยา&lt;br /&gt;&lt;br /&gt;

ชีวิตของลูกผู้ชายคนหนึ่ง&lt;br /&gt;
คำว่า ของ เป็นคำบุพบท แสดงความเป็นเจ้าของ "ของลูกผู้ชายคนหนึ่ง" ขยายคำว่า ชีวิต&lt;br /&gt;&lt;br /&gt;
ความพยายามที่ทุกคนมีอยู่ &lt;br /&gt;
คำว่า "ที่" เป็นคำประพันธสรรพนาม คือ สรรพนามที่ใช้แทนคำนามซึ่งอยู่ข้างหน้า (คือคำว่า "ความพยายาม") &lt;br /&gt;&lt;br /&gt;
ผู้สมัครสอบที่เป็นครูอัตราจ้าง&lt;br /&gt;
คำว่า "ที่" เป็นคำประพันธสรรพนาม&lt;br /&gt;&lt;br /&gt;
คำประพันธสรรพนาม คือคำใช้แทนคำนามหรือข้อความที่อยู่ข้างหน้า เช่น คนที่ขยัน เด็กที่ฉลาด เป็นต้น &lt;br /&gt;
คำประพันธสรรพนามมีอีกหลายคำ เช่น คำว่า ที่ ซึ่ง อัน &lt;br /&gt;&lt;br /&gt;

คำตอบที่ถูก คือ ข้อ 3 &lt;br /&gt;

	</explanation>
    <isExplain>yes</isExplain>
    <!-- ไม่แสดงป้าย คำอธิบาย ให้คลิก  - none -->
    <!-- แสดงป้าย คำอธิบาย ให้คลิก มีเฉลย+คำอธิบาย  - yes  -->
    <!-- แสดงป้าย คำอธิบาย ให้คลิก มีเฉลย+ไม่มีคำอธิบาย  - premium only  -->
    <!-- แสดงป้าย คำอธิบาย ให้คลิก ไม่เฉลย+ไม่มีคำอธิบาย  - disable answer  -->
  </thisQuestion>
  <!-- XX -->
  <thisQuestion>
    <qNum>id01518:date1627453500</qNum>
    <question>&lt;strong&gt;คำสั่ง: &lt;/strong&gt;ให้ท่านเลือกคำตอบที่ถูกต้องที่สุด&lt;br /&gt; &lt;br /&gt;

ข้อใดใช้สำนวน  &lt;b&gt;ไม่ถูกต้อง&lt;/b&gt;  &lt;br /&gt;

	</question>
    <choice_A>ผมกลัวเขาอยู่หมือนกัน แต่ก็ทนใจดีสู้เสือ</choice_A>
    <choice_B>เขาเขียนบทความยาวสิบหน้า แต่น้ำท่วมทุ่ง ผักบุ้งโหรงเหรง</choice_B>
    <choice_C>เขาไม่มี พวกพ้องให้พึ่งพาอาศัย เป็นคนหัวเดียวกระเทียมลีบแท้ ๆ</choice_C>
    <choice_D>เขาเป็นคนขวานผ่าซาก ชอบพูดจาว่าร้ายคนอื่นอยู่สมอ</choice_D>
    <choice_E>
    </choice_E>
    <correctAns>5</correctAns>
    <!-- A=2, B=3, C=4, D=5 -->
    <explanation>&lt;strong&gt;คำสั่ง: &lt;/strong&gt;ให้ท่านเลือกคำตอบที่ถูกต้องที่สุด&lt;br /&gt; &lt;br /&gt;

ข้อใดใช้สำนวน &lt;b&gt;ไม่ถูกต้อง&lt;\b&gt; &lt;br /&gt; &lt;br /&gt;

1. ผมกลัวเขาอยู่หมือนกัน แต่ก็ทนใจดีสู้เสือ  &lt;br /&gt;
2. เขาเขียนบทความยาวสิบหน้า แต่น้ำท่วมทุ่ง ผักบุ้งโหรงเหรง  &lt;br /&gt;
3. เขาไม่มี พวกพ้องให้พึ่งพาอาศัย เป็นคนหัวเดียวกระเทียมลีบแท้ ๆ &lt;br /&gt;
4. เขาเป็นคนขวานผ่าซาก ชอบพูดจาว่าร้ายคนอื่นอยู่สมอ ✔ &lt;br /&gt; &lt;br /&gt;


	คำอธิบาย&lt;br /&gt;&lt;br /&gt;

ข้อ 4 ใช้สำนวนผิดความหมาย  "ขวานผ่าซาก" หมายความว่า โผงผางไม่เกรงใจใคร ไม่ใช่ พูดจาว่าร้ายคนอื่น&lt;br /&gt;&lt;br /&gt;

คำตอบที่ถูก คือ ข้อ 4 &lt;br /&gt;


	</explanation>
    <isExplain>disable answer</isExplain>
    <!-- ไม่แสดงป้าย คำอธิบาย ให้คลิก  - none -->
    <!-- แสดงป้าย คำอธิบาย ให้คลิก มีเฉลย+คำอธิบาย  - yes  -->
    <!-- แสดงป้าย คำอธิบาย ให้คลิก มีเฉลย+ไม่มีคำอธิบาย  - premium only  -->
    <!-- แสดงป้าย คำอธิบาย ให้คลิก ไม่เฉลย+ไม่มีคำอธิบาย  - disable answer  -->
  </thisQuestion>
  <!-- XX -->
  <thisQuestion>
    <qNum>id01519:date1627453500</qNum>
    <question>&lt;strong&gt;คำสั่ง: &lt;/strong&gt;ให้ท่านเลือกคำตอบที่ถูกต้องที่สุด&lt;br /&gt; &lt;br /&gt;
ข้อใดใช้ภาษาเหมาะสมที่สุด&lt;br /&gt;

	</question>
    <choice_A>แม่ค้าขายส้มตำไก่ย่าง เป็นอาชีพที่มีรายได้ดี และไม่ตกงาน</choice_A>
    <choice_B>อาหารประเภทยำ มีรสชาติเผ็ดร้อนกลมกล่อมถูกปากคนไทย</choice_B>
    <choice_C>แม้ว่าฐานะของเราจะไม่ดีนัก พ่อแม่ก็ส่งให้ลูกทุกคนเรียนจบมหาวิทยาลัยได้</choice_C>
    <choice_D>เพราะว่าอาจารย์วิสูตรมีชื่อเสียงทางด้านดนตรีไทยมาก ผมจึงเลือกลงทะเบียนเรียนกับท่าน</choice_D>
    <choice_E>
    </choice_E>
    <correctAns>5</correctAns>
    <!-- A=2, B=3, C=4, D=5 -->
    <explanation>&lt;strong&gt;คำสั่ง: &lt;/strong&gt;ให้ท่านเลือกคำตอบที่ถูกต้องที่สุด&lt;br /&gt; &lt;br /&gt;
ข้อใดใช้ภาษาเหมาะสมที่สุด&lt;br /&gt;&lt;br /&gt;

1. แม่ค้าขายส้มตำไก่ย่างเป็นอาชีพที่มีรายได้ดีและเป็นอิสระ&lt;br /&gt;
2. อาหารประเภทต้มยำ มีรสชาติเผ็ดร้อนกลมกล่อมถูกปากคนไทย&lt;br /&gt;
3. แม้ว่าฐานะของเราจะไม่ดีนัก พ่อแม่ก็ส่งให้ลูกทุกคนเรียนจบมหาวิทยาลัยได้&lt;br /&gt;
4. เพราะว่าอาจารย์วิสูตรมีชื่อเสียงทางด้านดนตรีไทยมาก ผมจึงเลือกลงทะเบียนเรียนกับท่าน ✔&lt;br /&gt;&lt;br /&gt;

	คำอธิบาย&lt;br /&gt;&lt;br /&gt;
ข้อ 1. แม่ค้าขายส้มตำ ไม่ใช่อาชีพ แต่เป็นคน ถ้าเป็นอาชีพ ควรพูดว่า การขายส้มตำ&lt;br /&gt;&lt;br /&gt;

ข้อ 2. ใช้คำไม่เหมาะสม คำว่า เผ็ดร้อน ควรใช้กับคำว่า "จัดจ้าน" มากกว่า "กลมกล่อม.png&quot;&gt;&lt;br /&gt;&lt;br /&gt;

ข้อ 3. ใช้คำเชื่อมไม่เหมาะสม คำว่า "แม้ว่า" ควรใช้คู่กับ "แต่.png&quot;&gt;&lt;br /&gt;
แม้ว่าฐานะของเราจะไม่ดีนัก แต่พ่อแม่ก็ส่งให้ลูกทุกคนเรียนจบมหาวิทยาลัยได้&lt;br /&gt;&lt;br /&gt;

ข้อ 4. ถูกต้องแล้ว ใช้คำเชื่อมเหมาะสม "แม้ว่า" .... "แต่.png&quot;&gt;&lt;br /&gt;&lt;br /&gt;

คำตอบที่ถูก คือ ข้อ  &lt;br /&gt;

	</explanation>
    <isExplain>disable answer</isExplain>
    <!-- ไม่แสดงป้าย คำอธิบาย ให้คลิก  - none -->
    <!-- แสดงป้าย คำอธิบาย ให้คลิก มีเฉลย+คำอธิบาย  - yes  -->
    <!-- แสดงป้าย คำอธิบาย ให้คลิก มีเฉลย+ไม่มีคำอธิบาย  - premium only  -->
    <!-- แสดงป้าย คำอธิบาย ให้คลิก ไม่เฉลย+ไม่มีคำอธิบาย  - disable answer  -->
  </thisQuestion>
  <!-- XX -->
  <thisQuestion>
    <qNum>id01520:date1627453500</qNum>
    <question>&lt;strong&gt;คำสั่ง: &lt;/strong&gt;ให้ท่านเลือกคำตอบที่ถูกต้องที่สุด&lt;br /&gt; &lt;br /&gt;
ประโยคใดใช้ภาษาได้เหมาะสมที่สุด &lt;br /&gt;

	</question>
    <choice_A>ทีมฟุตบอลของไทยชนะกราวรูดได้เหรียญทอง</choice_A>
    <choice_B>ข้าพเจ้ารู้สึกภาคภูมิและยินดีเป็นอย่างยิ่งที่ได้มาอภิปรายวันนี้</choice_B>
    <choice_C>เราจะลงโทษเขาอย่างไรดี จึงจะเหมาะสมกับความผิดของเขา</choice_C>
    <choice_D>มีผู้กล่าวเปรียบเปรยไว้ว่า รถไฟของญี่ปุ่นขบวนนี้ วิ่งได้เร็วกว่ากระสุนปืน</choice_D>
    <choice_E>
    </choice_E>
    <correctAns>4</correctAns>
    <!-- A=2, B=3, C=4, D=5 -->
    <explanation>&lt;strong&gt;คำสั่ง: &lt;/strong&gt;ให้ท่านเลือกคำตอบที่ถูกต้องที่สุด&lt;br /&gt; &lt;br /&gt;
ประโยคใดใช้ภาษาได้เหมาะสมที่สุด &lt;br /&gt;&lt;br /&gt;

1. ทีมฟุตบอลของไทยชนะกราวรูดได้เหรียญทอง  &lt;br /&gt;
2. ข้าพเจ้ารู้สึกภาคภูมิและยินดีเป็นอย่างยิ่งที่ได้มาอภิปรายวันนี้  &lt;br /&gt;
3. เราจะลงโทษเขาอย่างไรดีจึงจะเหมาะสมกับความผิดของเขา ✔ &lt;br /&gt;
4. มีผู้กล่าวเปรียบเปรยไว้ว่า รถไฟของญี่ปุ่นขบวนนี้วิ่งได้เร็ว กว่ากระสุนปีน &lt;br /&gt;&lt;br /&gt;

	คำอธิบาย&lt;br /&gt;&lt;br /&gt;

ข้อ 1. ใช้คำผิด คำว่า "กราวรูด" ควรเปลี่ยนเป็น "รวด.png&quot;&gt;&lt;br /&gt;
รวด- ติดต่อกันหลายครั้ง เช่น ชนะ ๕ ครั้งรวด &lt;br /&gt;
ชนะรวด  แพ้กราวรูด&lt;br /&gt;&lt;br /&gt;

ข้อ 2. คำว่า "ภาคภูมิ" ควรเปลี่ยนเป็น "ภูมิใจ.png&quot;&gt;&lt;br /&gt;
ภาคภูมิ - มีสง่า, ผึ่งผาย, เช่น เขาแต่งตัวภาคภูมิ&lt;br /&gt;
ภูมิใจ - รู้สึกว่ามีเกียรติยศ&lt;br /&gt;&lt;br /&gt;

ข้อ 3. เหมาะสม ถูกต้องแล้ว&lt;br /&gt;&lt;br /&gt;

ข้อ 4. ควรใช้คำว่า "เปรียบเทียบ" แทนคำว่า "เปรียบเปรย.png&quot;&gt;&lt;br /&gt;
เปรียบเทียบ - พิจารณาเทียบเคียงให้เห็นลักษณะที่เหมือนกันและต่างกัน&lt;br /&gt;
เปรียบเปรย - อาการที่พูดว่ากระทบกระเทียบไม่เจาะจง&lt;br /&gt;&lt;br /&gt;


คำตอบที่ถูก คือ ข้อ 3  &lt;br /&gt;


	</explanation>
    <isExplain>disable answer</isExplain>
    <!-- ไม่แสดงป้าย คำอธิบาย ให้คลิก  - none -->
    <!-- แสดงป้าย คำอธิบาย ให้คลิก มีเฉลย+คำอธิบาย  - yes  -->
    <!-- แสดงป้าย คำอธิบาย ให้คลิก มีเฉลย+ไม่มีคำอธิบาย  - premium only  -->
    <!-- แสดงป้าย คำอธิบาย ให้คลิก ไม่เฉลย+ไม่มีคำอธิบาย  - disable answer  -->
  </thisQuestion>
  <!-- XX -->
  <thisQuestion>
    <qNum>id01521:date1627453500</qNum>
    <question>&lt;strong&gt;คำสั่ง: &lt;/strong&gt;ให้ท่านเลือกคำตอบที่ถูกต้องที่สุด&lt;br /&gt; &lt;br /&gt;
ข้อใดใช้คำถูกต้อง&lt;br /&gt;

	</question>
    <choice_A>ฆาตกรหัวแข็งให้การปฏิเสธข้อกล่าวหาทุกข้อ</choice_A>
    <choice_B>ต้อยมีผมหยักโศกซึ่งเหมือนกับคุณพ่อของเขา</choice_B>
    <choice_C>ครูใหญ่อุปการคุณฉันมาตลอดตั้งแต่เด็กจนจบการศึกษา</choice_C>
    <choice_D>การลดความอ้วนให้ได้ผลดีต้องไม่กินจุบจิบตลอดวันอย่างนี้</choice_D>
    <choice_E>
    </choice_E>
    <correctAns>5</correctAns>
    <!-- A=2, B=3, C=4, D=5 -->
    <explanation>&lt;strong&gt;คำสั่ง: &lt;/strong&gt;ให้ท่านเลือกคำตอบที่ถูกต้องที่สุด&lt;br /&gt; &lt;br /&gt;
ข้อใดใช้คำถูกต้อง&lt;br /&gt;&lt;br /&gt;

1. ฆาตกรหัวแข็งให้การปฏิเสธข้อกล่าวหาทุกข้อ&lt;br /&gt;
2. ต้อยมีผมหยักโศกซึ่งเหมือนกับคุณพ่อของเขา&lt;br /&gt;
3. ครูใหญ่อุปการคุณฉันมาตลอดตั้งแต่เด็กจนจบการศึกษา&lt;br /&gt;
4. การลดความอ้วนให้ได้ผลดีต้องไม่กินจุบจิบตลอดวันอย่างนี้ ✔&lt;br /&gt;&lt;br /&gt;

	คำอธิบาย&lt;br /&gt;&lt;br /&gt;

ข้อ 1. คำว่า "หัวแข็ง" ควรใช้คำว่า "ปากแข็ง" แทน&lt;br /&gt;
หัวแข็ง - กระด้าง, ว่ายาก, เช่น เขาเป็นคนหัวแข็ง ผู้ใหญ่พูดเท่าไรก็ไม่ยอมเชื่อฟัง&lt;br /&gt;
ปากแข็ง - พูดยืนยันหรือเถียงอย่างดื้อดันไม่ยอมจำนนข้อเท็จจริง&lt;br /&gt;&lt;br /&gt;

ข้อ 2. คำว่า หยักโศก ที่ถูกคือ หยักศก&lt;br /&gt;&lt;br /&gt;

ข้อ 3. คำว่า อุปการคุณ ไม่ใช่คำกริยา แต่หมายถึงผู้มีอุปการะ เช่น  ร้านค้ามักใช้คำว่า ผู้มีอุปการคุณ กับลูกค้าที่ช่วยซื้อสินค้าหรือบริการของตน&lt;br /&gt;
คำว่า "อุปการะ" หมายถึง ช่วยเหลือเกื้อกูล แต่มักใช้กับการช่วยเหลือเลี้ยงดูที่ไม่ใช่งานในหน้าที่ เช่น พ่อแม่กับลูกจะไม่ใช้คำว่า อุปการะ ไม่ว่าจะเป็นพ่อแม่เลี้ยงดูลูกหรือลูกเลี้ยงดูพ่อแม่ก็ตาม. เราใช้คำว่า อุปการะ เมื่อช่วยเหลือเลี้ยงดูเด็กกำพร้า ช่วยเหลือเกื้อกูลสถาบันหรือองค์กรต่าง ๆ&lt;br /&gt;
ประโยคที่ถูกคือ "ครูใหญ่เป็นผู้มีอุปการคุณของฉันมาตลอด ....png&quot;&gt;&lt;br /&gt;&lt;br /&gt;

ข้อ 4. ถูกต้อง กินจุบจิบ ไม่ใช่ กินจุกจิก&lt;br /&gt;
จุบจิบ - อาการที่กินพร่ำเพรื่อทีละเล็กทีละน้อย&lt;br /&gt;&lt;br /&gt;

คำตอบที่ถูก คือ ข้อ 4 &lt;br /&gt;


	</explanation>
    <isExplain>disable answer</isExplain>
    <!-- ไม่แสดงป้าย คำอธิบาย ให้คลิก  - none -->
    <!-- แสดงป้าย คำอธิบาย ให้คลิก มีเฉลย+คำอธิบาย  - yes  -->
    <!-- แสดงป้าย คำอธิบาย ให้คลิก มีเฉลย+ไม่มีคำอธิบาย  - premium only  -->
    <!-- แสดงป้าย คำอธิบาย ให้คลิก ไม่เฉลย+ไม่มีคำอธิบาย  - disable answer  -->
  </thisQuestion>
  <!-- XX -->
  <thisQuestion>
    <qNum>id01522:date1627453500</qNum>
    <question>&lt;strong&gt;คำสั่ง: &lt;/strong&gt;ให้ท่านเลือกคำตอบที่ถูกต้องที่สุด&lt;br /&gt; &lt;br /&gt;
ข้อใดใช้คำถูกต้อง&lt;br /&gt;

	</question>
    <choice_A>สันติเอาพู่กันจุ้มสีน้ำ และระบายลงบนแผ่นกระดาษ</choice_A>
    <choice_B>ควรดื่มน้ำสะอาด ไม่มีสารอื่นปะปนซึ่งจะเป็นอันตรายต่อสุขภาพ</choice_B>
    <choice_C>นักเรียนคนนี้ปัญญาดี สามารถตอบคำถามยาก ๆ ได้อย่างเฉียบพลัน</choice_C>
    <choice_D>ตำรวจยุคปัจจุบันทำงานได้อย่างเร็วไว เพียงไม่กี่เดือนก็สามารถคลี่คลายคดีหวย 30 ล้านได้</choice_D>
    <choice_E>
    </choice_E>
    <correctAns>2</correctAns>
    <!-- A=2, B=3, C=4, D=5 -->
    <explanation>&lt;strong&gt;คำสั่ง: &lt;/strong&gt;ให้ท่านเลือกคำตอบที่ถูกต้องที่สุด&lt;br /&gt; &lt;br /&gt;
ข้อใดใช้คำถูกต้อง&lt;br /&gt;&lt;br /&gt;

1. สันติเอาพู่กันจุ้มสีน้ำ และระบายลงบนแผ่นกระดาษ ✔&lt;br /&gt;
2. ควรดื่มน้ำสะอาด ไม่มีสารอื่นปะปนซึ่งจะเป็นอันตรายต่อสุขภาพ&lt;br /&gt;
3. นักเรียนคนนี้ปัญญาดี สามารถตอบคำถามยาก ๆ ได้อย่างเฉียบพลัน&lt;br /&gt;
4. ตำรวจยุคปัจจุบันทำงานได้อย่างเร็วไว เพียงไม่กี่เดือนก็สามารถคลี่คลายคดีหวย 30 ล้านได้&lt;br /&gt;&lt;br /&gt;


	คำอธิบาย&lt;br /&gt;&lt;br /&gt;

ข้อ 1: ถูกต้องแล้ว &lt;br /&gt;
จุ่ม - เอาสิ่งใดสิ่งหนึ่งจ่อมลงไปในของเหลวแล้วยกขึ้น เช่น เอาผ้าจุ่มนํ้า&lt;br /&gt;
จุ้ม - เอาสิ่งใดสิ่งหนึ่งชุบหรือจุ่มลงไปในของเหลว เช่น เอาปากกาจุ้มหมึก&lt;br /&gt;&lt;br /&gt;

ข้อ 2: ควรใช้คำว่า เจือปน แทน ปะปน&lt;br /&gt;
เจือปน - เอาส่วนน้อยประสมลงในส่วนมากเพื่อให้ระคนปนเป็นเนื้อเดียวกัน เช่น สารเจือปน&lt;br /&gt;
ปะปน - ปนกัน (มักใช้ในลักษณะที่สิ่งต่างชนิดต่างประเภทระคนปนกัน) เช่น เขาวิ่งปะปนไปในฝูงชน&lt;br /&gt;&lt;br /&gt;

ข้อ 3: ควรใช้คำว่า ฉับพลัน&lt;br /&gt;
ฉับพลัน - ทันทีทันใด, ทันทีทันควัน&lt;br /&gt;
เฉียบพลัน - อาการที่เริ่มอย่างรวดเร็วและรุนแรงมาก (มักใช้แก่อาการของโรค) เช่น หัวใจวายเฉียบพลัน&lt;br /&gt;&lt;br /&gt;

ข้อ 4: ควรใช้ว่า ว่องไว หรือ รวดเร็ว&lt;br /&gt;
ว่องไว - รวดเร็ว, คล่องแคล่ว, ปราดเปรียว, ปราดเปรื่อง, เช่น ทำงานว่องไว มีปฏิภาณว่องไว&lt;br /&gt;
เร็วไว - รีบ ด่วน เช่น ออกไปอย่างเร็วไว&lt;br /&gt;&lt;br /&gt;


คำตอบที่ถูก คือ ข้อ 1 &lt;br /&gt;


	</explanation>
    <isExplain>disable answer</isExplain>
    <!-- ไม่แสดงป้าย คำอธิบาย ให้คลิก  - none -->
    <!-- แสดงป้าย คำอธิบาย ให้คลิก มีเฉลย+คำอธิบาย  - yes  -->
    <!-- แสดงป้าย คำอธิบาย ให้คลิก มีเฉลย+ไม่มีคำอธิบาย  - premium only  -->
    <!-- แสดงป้าย คำอธิบาย ให้คลิก ไม่เฉลย+ไม่มีคำอธิบาย  - disable answer  -->
  </thisQuestion>
  <!-- XX -->
  <thisQuestion>
    <qNum>id01523:date1627453500</qNum>
    <question>&lt;strong&gt;คำสั่ง: &lt;/strong&gt;ให้ท่านเลือกคำตอบที่ถูกต้องที่สุด&lt;br /&gt; &lt;br /&gt;
ข้อใดใช้คำถูกต้อง&lt;br /&gt;

	</question>
    <choice_A>มานะเป็นคนเฉียบแหลม มีปัญญาและไหวพริบดีมาก</choice_A>
    <choice_B>งานเขียนของเขาแสดงออกถึงความคิดที่หลักแหลม </choice_B>
    <choice_C>คุณต้องรีบไปสำรองตั๋วเครื่องบิน ก่อนที่นั่งจะเต็มหมด</choice_C>
    <choice_D>เขาเจียดเงินไว้ สำหรับใช้จ่ายเมื่อคราวจำเป็นคับขัน</choice_D>
    <choice_E>
    </choice_E>
    <correctAns>3</correctAns>
    <!-- A=2, B=3, C=4, D=5 -->
    <explanation>&lt;strong&gt;คำสั่ง: &lt;/strong&gt;ให้ท่านเลือกคำตอบที่ถูกต้องที่สุด&lt;br /&gt; &lt;br /&gt;
ข้อใดใช้คำถูกต้อง&lt;br /&gt;&lt;br /&gt;

1. มานะเป็นคนเฉียบแหลม มีปัญญาและไหวพริบดีมาก&lt;br /&gt;
2. งานเขียนของเขาแสดงออกถึงความคิดที่หลักแหลม ✔&lt;br /&gt;
3. คุณต้องรีบไปสำรองตั๋วเครื่องบิน ก่อนที่นั่งจะเต็มหมด&lt;br /&gt;
4. เขาเจียดเงินไว้ สำหรับใช้จ่ายเมื่อคราวจำเป็นคับขัน&lt;br /&gt;&lt;br /&gt;

	คำอธิบาย&lt;br /&gt;&lt;br /&gt;

คำตอบที่ถูก คือ ข้อ  &lt;br /&gt;
ข้อ 1 ควรใช้คำว่า เฉลียวฉลาด&lt;br /&gt;
เฉลียวฉลาด - มีปัญญาและไหวพริบด&lt;br /&gt;&lt;br /&gt;ี

ข้อ 2 ถูกต้องแล้ว&lt;br /&gt;
หลักแหลม - คมคาย เช่น วาจาหลักแหลม, เฉียบแหลม เช่น ความคิดหลักแหลม&lt;br /&gt;&lt;br /&gt;

ข้อ 3: ควรใช้คำว่า จอง&lt;br /&gt;
จอง - มั่นหมายไว้, ขอกำหนดไว&lt;br /&gt;้
สำรอง - ที่เตรียมเผื่อไว้ เช่น อาหารสำรอง ตัวสำรอง&lt;br /&gt;&lt;br /&gt;

ข้อ 4: ควรใช้คำว่า ออม&lt;br /&gt;
ออม - เก็บหอมรอมริบ เช่น ออมทรัพย์ ออมสิน&lt;br /&gt;
เจียด - แบ่งปันแต่น้อย, ขอแบ่งปันบ้าง, เช่น เขามีน้อยขอเจียดเอามาบ้าง&lt;br /&gt;&lt;br /&gt;

คำตอบที่ถูก คือ ข้อ 2 &lt;br /&gt;

	</explanation>
    <isExplain>disable answer</isExplain>
    <!-- ไม่แสดงป้าย คำอธิบาย ให้คลิก  - none -->
    <!-- แสดงป้าย คำอธิบาย ให้คลิก มีเฉลย+คำอธิบาย  - yes  -->
    <!-- แสดงป้าย คำอธิบาย ให้คลิก มีเฉลย+ไม่มีคำอธิบาย  - premium only  -->
    <!-- แสดงป้าย คำอธิบาย ให้คลิก ไม่เฉลย+ไม่มีคำอธิบาย  - disable answer  -->
  </thisQuestion>
  <!-- XX -->
  <thisQuestion>
    <qNum>id01524:date1627453500</qNum>
    <question>&lt;strong&gt;คำสั่ง: &lt;/strong&gt;ให้ท่านเลือกคำตอบที่ถูกต้องที่สุด&lt;br /&gt; &lt;br /&gt;
ข้อใดใช้คำ&lt;b&gt;ไม่ถูกต้อง&lt;/b&gt;&lt;br /&gt;

	</question>
    <choice_A>ก่อนกินยา ต้องอ่านฉลากยาให้เข้าใจ และทำตามอย่างเคร่งครัด</choice_A>
    <choice_B>ให้ผู้ขายฉลากกินแบ่งรัฐบาล ขายได้ไม่เกิน ราคาฉบับละ 80 บาท</choice_B>
    <choice_C>รายการชิงทอง กำหนดวันจับสลากผู้โชคดีได้รับทอง 5	บาท ในวันเสาร์นี้</choice_C>
    <choice_D>เขาทำสลากให้เด็กๆ จับ เพื่อรับของขวัญในวันปีใหม่</choice_D>
    <choice_E>
    </choice_E>
    <correctAns>3</correctAns>
    <!-- A=2, B=3, C=4, D=5 -->
    <explanation>&lt;strong&gt;คำสั่ง: &lt;/strong&gt;ให้ท่านเลือกคำตอบที่ถูกต้องที่สุด&lt;br /&gt; &lt;br /&gt;

ข้อใดใช้คำ&lt;b&gt;ไม่ถูกต้อง&lt;/b&gt; &lt;br /&gt;&lt;br /&gt;

1. ก่อนกินยา ต้องอ่านฉลากยาให้เข้าใจ และทำตามอย่างเคร่งครัด&lt;br /&gt;
2. ให้ผู้ขายฉลากกินแบ่งรัฐบาล ขายได้ไม่เกิน ราคาฉบับละ 80 บาท ✔ &lt;br /&gt;
3. รายการชิงทอง กำหนดวันจับสลากผู้โชคดีได้รับทอง 5	บาท ในวันเสาร์นี้&lt;br /&gt;
4. เขาทำสลากให้เด็กๆ จับ เพื่อรับของขวัญในวันปีใหม่&lt;br /&gt;&lt;br /&gt;

	คำอธิบาย&lt;br /&gt;&lt;br /&gt;

สลาก - 
   (๑) สิ่งเช่นติ้ว ตั๋ว หรือแผ่นกระดาษเล็ก ๆ เป็นต้น ซึ่งทำเป็นเครื่องหมายกำหนดไว้เนื่องในการเสี่ยงโชคเสี่ยงทายเป็นต้น &lt;br /&gt;
    (๒) หมายถึง ป้ายบอกชื่อยา ใช้ปิดขวดยารักษาโรค เรียกว่า สลากยา ก็ได้ &lt;br /&gt;&lt;br /&gt;

ฉลาก - 
   (๑) สิ่งเช่นติ้ว ตั๋ว หรือแผ่นกระดาษเล็ก ๆ เป็นต้น ซึ่งทำเป็นเครื่องหมายกำหนดไว้เนื่องในการเสี่ยงโชคเสี่ยงทายเป็นต้น&lt;br /&gt;

    (๒) น. ป้ายบอกชื่อยา ใช้ปิดขวดยารักษาโรค เรียกว่า ฉลากยา&lt;br /&gt;

    (๓) น. สลาก ก็ว่า&lt;br /&gt;

     (๔)  (กฎ) น. รูป รอยประดิษฐ์ เครื่องหมาย หรือข้อความใด ๆ ที่แสดงไว้ที่ภาชนะหรือหีบห่อบรรจุสินค้า เช่น ฉลากยา ฉลากเครื่องสำอาง&lt;br /&gt;&lt;br /&gt;

ข้อ 2: คำที่ถูกคือ สลากกินแบ่งรัฐบาล&lt;br /&gt;&lt;br /&gt;

คำตอบที่ถูก คือ ข้อ 2 &lt;br /&gt;


	</explanation>
    <isExplain>disable answer</isExplain>
    <!-- ไม่แสดงป้าย คำอธิบาย ให้คลิก  - none -->
    <!-- แสดงป้าย คำอธิบาย ให้คลิก มีเฉลย+คำอธิบาย  - yes  -->
    <!-- แสดงป้าย คำอธิบาย ให้คลิก มีเฉลย+ไม่มีคำอธิบาย  - premium only  -->
    <!-- แสดงป้าย คำอธิบาย ให้คลิก ไม่เฉลย+ไม่มีคำอธิบาย  - disable answer  -->
  </thisQuestion>
  <!-- XX -->
  <thisQuestion>
    <qNum>id01525:date1627453500</qNum>
    <question>&lt;strong&gt;คำสั่ง: &lt;/strong&gt;ให้ท่านเลือกคำตอบที่ถูกต้องที่สุด&lt;br /&gt; &lt;br /&gt;
ข้อใดใช้คำ&lt;b&gt;ไม่ถูกต้อง&lt;/b&gt; &lt;br /&gt;

	</question>
    <choice_A>จากสภาพเศรษฐกิจที่ทรุดโทรมลง ทำให้เกิดมีผู้ร้ายชุกชุม</choice_A>
    <choice_B>โดยปกติในเมืองใหญ่ มักจะเห็นตึกสูงระฟ้ามีอยู่ชุกชุมโดยทั่วไป</choice_B>
    <choice_C>ที่ริมฝั่งน้ำหน้าวัดกลาง มีปลาหลายชนิดชุกชุมมาก เพราะทางวัดอนุรักษ์เอาไว้</choice_C>
    <choice_D>ประมาณเดือนเมษายน จะเห็นมีมะม่วงสุกในตลาดมีอยู่อย่างดกดื่น</choice_D>
    <choice_E>
    </choice_E>
    <correctAns>3</correctAns>
    <!-- A=2, B=3, C=4, D=5 -->
    <explanation>&lt;strong&gt;คำสั่ง: &lt;/strong&gt;ให้ท่านเลือกคำตอบที่ถูกต้องที่สุด&lt;br /&gt; &lt;br /&gt;

ข้อใดใช้คำ&lt;b&gt;ไม่ถูกต้อง&lt;br /&gt;&lt;br /&gt;

1. จากสภาพเศรษฐกิจที่ทรุดโทรมลง ทำให้เกิดมีผู้ร้ายชุกชุม&lt;br /&gt;
2. โดยปกติในเมืองใหญ่ มักจะเห็นตึกสูงระฟ้ามีอยู่ชุกชุมโดยทั่วไป ✔&lt;br /&gt;
3. ที่ริมฝั่งน้ำหน้าวัดกลาง มีปลาหลายชนิดชุกชุมมาก เพราะทางวัดอนุรักษ์เอาไว&lt;br /&gt;
4. ประมาณเดือนเมษายน จะเห็นมีมะม่วงสุกในตลาดมีอยู่อย่างดกดื่น&lt;br /&gt;&lt;br /&gt;


	คำอธิบาย&lt;br /&gt;&lt;br /&gt;

ชุกชุม - มีดื่นดาษ, มีมากมาย, เช่น แถวนี้ขโมยชุกชุม&lt;br /&gt;
ดกดื่น - มากหลาย, มีอยู่ทั่วไป, เช่น สวนนี้มีกล้วยน้ำว้าอยู่ดกดื่น หน้านี้มีมะปรางดกดื่น&lt;br /&gt;
ดาษดื่น - เกลื่อนกลาด, มากหลาย, ดื่นดาษ ก็ว่า&lt;br /&gt;&lt;br /&gt;


ข้อ 2 ควรใช้คำว่า ดกดื่น หรือ ดาษดื่น แทนคำว่า ชุกชุม&lt;br /&gt;&lt;br /&gt;

คำตอบที่ถูก คือ ข้อ 2 &lt;br /&gt;


	</explanation>
    <isExplain>disable answer</isExplain>
    <!-- ไม่แสดงป้าย คำอธิบาย ให้คลิก  - none -->
    <!-- แสดงป้าย คำอธิบาย ให้คลิก มีเฉลย+คำอธิบาย  - yes  -->
    <!-- แสดงป้าย คำอธิบาย ให้คลิก มีเฉลย+ไม่มีคำอธิบาย  - premium only  -->
    <!-- แสดงป้าย คำอธิบาย ให้คลิก ไม่เฉลย+ไม่มีคำอธิบาย  - disable answer  -->
  </thisQuestion>
  <!-- XX -->
  <thisQuestion>
    <qNum>id01526:date1627453500</qNum>
    <question>&lt;strong&gt;คำสั่ง: &lt;/strong&gt;ให้ท่านเลือกคำตอบที่ถูกต้องที่สุด&lt;br /&gt; &lt;br /&gt;
ข้อใดใช้คำถูกต้อง&lt;br /&gt;

	</question>
    <choice_A>คนขับรถยอมรับผิด และยอมชดเชยค่าเสียหายทั้งหมด</choice_A>
    <choice_B>วันเสาร์นี้ อาจารย์สอนชดเชยช่วงที่ไปราชการ</choice_B>
    <choice_C>ฝนตกหนัก น้ำท่วม โรงเรียนปิด ทำให้ต้องเปิดสอนชดใช้ในวันหยุด</choice_C>
    <choice_D>นี่เป็นเงินชดเชย ที่คุณได้ออกเงินไป ก่อนล่วงหน้าแล้ว</choice_D>
    <choice_E>
    </choice_E>
    <correctAns>3</correctAns>
    <!-- A=2, B=3, C=4, D=5 -->
    <explanation>&lt;strong&gt;คำสั่ง: &lt;/strong&gt;ให้ท่านเลือกคำตอบที่ถูกต้องที่สุด&lt;br /&gt; &lt;br /&gt;

ข้อใดใช้คำถูกต้อง&lt;br /&gt;&lt;br /&gt;

1. คนขับรถยอมรับผิด และยอมชดเชยค่าเสียหายทั้งหมด&lt;br /&gt;
2. วันเสาร์นี้ อาจารย์สอนชดเชยช่วงที่ไปราชการ ✔&lt;br /&gt;
3. ฝนตกหนัก น้ำท่วม โรงเรียนปิด ทำให้ต้องเปิดสอนชดใช้ในวันหยุด&lt;br /&gt;
4. นี่เป็นเงินชดเชย ที่คุณได้ออกเงินไป ก่อนล่วงหน้าแล้ว&lt;br /&gt;&lt;br /&gt;

	คำอธิบาย&lt;br /&gt;&lt;br /&gt;

ชดเชย - ใช้แทนสิ่งที่เสียไป เช่น เมื่อคืนนอนน้อย เดี๋ยวบ่ายนี้ต้องนอนชดเชยเสียหน่อย&lt;br /&gt;
ชดใช้ - ใช้ค่าใช้จ่ายที่ทดรองจ่ายไปก่อนแล้ว, ให้ทดแทนสิ่งที่ใช้หรือเสียไป เช่น ชดใช้ค่าเสียหาย &lt;br /&gt;&lt;br /&gt;

ข้อ 1 ควรใช้ว่า ชดใช้&lt;br /&gt;
ข้อ 2 ถูกต้องแล้ว&lt;br /&gt;
ข้อ 3 ควรใช้ว่าสอนชดเชย&lt;br /&gt;
ข้อ 4 ควรใช้ว่า ชดใช้&lt;br /&gt;&lt;br /&gt;


คำตอบที่ถูก คือ ข้อ 2 &lt;br /&gt;


	</explanation>
    <isExplain>disable answer</isExplain>
    <!-- ไม่แสดงป้าย คำอธิบาย ให้คลิก  - none -->
    <!-- แสดงป้าย คำอธิบาย ให้คลิก มีเฉลย+คำอธิบาย  - yes  -->
    <!-- แสดงป้าย คำอธิบาย ให้คลิก มีเฉลย+ไม่มีคำอธิบาย  - premium only  -->
    <!-- แสดงป้าย คำอธิบาย ให้คลิก ไม่เฉลย+ไม่มีคำอธิบาย  - disable answer  -->
  </thisQuestion>
  <!-- XX -->
  <thisQuestion>
    <qNum>id01527:date1627453500</qNum>
    <question>&lt;strong&gt;คำสั่ง: &lt;/strong&gt;ให้ท่านเลือกคำตอบที่ถูกต้องที่สุด&lt;br /&gt; &lt;br /&gt;
ข้อใดใช้คำถูกต้อง&lt;br /&gt;

	</question>
    <choice_A>เขาถูกเพื่อนเชื้อเชิญให้ร่วมกระทำความผิด</choice_A>
    <choice_B>เมื่อมีแขกมาเยี่ยม เราควรชักชวนให้เข้ามานั่งพักก่อน</choice_B>
    <choice_C>หญิงสาวโกรธมาก ที่ชายหนุ่มมาชมเชยแล้วทิ้งไป</choice_C>
    <choice_D>สุดาได้รับรางวัลชมเชย ในการประกวดร้องเพลงลูกทุ่ง</choice_D>
    <choice_E>
    </choice_E>
    <correctAns>5</correctAns>
    <!-- A=2, B=3, C=4, D=5 -->
    <explanation>&lt;strong&gt;คำสั่ง: &lt;/strong&gt;ให้ท่านเลือกคำตอบที่ถูกต้องที่สุด&lt;br /&gt; &lt;br /&gt;

ข้อใดใช้คำถูกต้อง&lt;br /&gt;&lt;br /&gt;

1. เขาถูกเพื่อนเชื้อเชิญให้ร่วมกระทำความผิด&lt;br /&gt;
2. เมื่อมีแขกมาเยี่ยม เราควรชักชวนให้เข้ามานั่งพักก่อน&lt;br /&gt;
3. หญิงสาวโกรธมาก ที่ชายหนุ่มมาชมเชยแล้วทิ้งไป&lt;br /&gt;
4. สุดาได้รับรางวัลชมเชย ในการประกวดร้องเพลงลูกทุ่ง ✔ &lt;br /&gt;&lt;br /&gt;

	คำอธิบาย&lt;br /&gt;&lt;br /&gt;

ข้อ 1 ควรใช้คำว่า ชักชวน&lt;br /&gt;
ชักชวน - ชวนให้ทำด้วยกัน&lt;br /&gt;
เชื้อเชิญ - เชิญผู้มาหาด้วยความสุภาพอ่อนน้อม&lt;br /&gt;&lt;br /&gt;

ข้อ 2 ควรใช้คำว่า เชื้อเชิญ&lt;br /&gt;&lt;br /&gt;

ข้อ 3 ควรใช้คำว่า เชยชม&lt;br /&gt;
เชยชม - จับต้องเล้าโลม, กอดจูบ&lt;br /&gt;&lt;br /&gt;

ข้อ 4 ถูกต้องแล้ว รางวัลชมเชย&lt;br /&gt;&lt;br /&gt;

คำตอบที่ถูก คือ ข้อ 4 &lt;br /&gt;


	</explanation>
    <isExplain>disable answer</isExplain>
    <!-- ไม่แสดงป้าย คำอธิบาย ให้คลิก  - none -->
    <!-- แสดงป้าย คำอธิบาย ให้คลิก มีเฉลย+คำอธิบาย  - yes  -->
    <!-- แสดงป้าย คำอธิบาย ให้คลิก มีเฉลย+ไม่มีคำอธิบาย  - premium only  -->
    <!-- แสดงป้าย คำอธิบาย ให้คลิก ไม่เฉลย+ไม่มีคำอธิบาย  - disable answer  -->
  </thisQuestion>
  <!-- XX -->
  <thisQuestion>
    <qNum>id01528:date1627453500</qNum>
    <question>&lt;strong&gt;คำสั่ง: &lt;/strong&gt;ให้ท่านเลือกคำตอบที่ถูกต้องที่สุด&lt;br /&gt; &lt;br /&gt;
ข้อใดใช้คำถูกต้อง&lt;br /&gt;

	</question>
    <choice_A>ตำรวจเชิญตัวสมศักดิ์เข้าพบ เพื่ออธิบายข้อกล่าวหา</choice_A>
    <choice_B>ธนาวุฒิเข้าพบคณะกรรมการ เพื่ออธิบายข้อเท็จจริง</choice_B>
    <choice_C>ครูสมทรงอธิบายเรื่องสภาพแวดล้อมได้อย่างชัดเจน</choice_C>
    <choice_D>นายวิชัย เขียนบันทึกข้อความ อธิบายเหตุผลการไม่เข้าร่วมประชุม</choice_D>
    <choice_E>
    </choice_E>
    <correctAns>4</correctAns>
    <!-- A=2, B=3, C=4, D=5 -->
    <explanation>&lt;strong&gt;คำสั่ง: &lt;/strong&gt;ให้ท่านเลือกคำตอบที่ถูกต้องที่สุด&lt;br /&gt; &lt;br /&gt;

ข้อใดใช้คำถูกต้อง&lt;br /&gt;&lt;br /&gt;

1. ตำรวจเชิญตัวสมศักดิ์เข้าพบ เพื่ออธิบายข้อกล่าวหา&lt;br /&gt;
2. ธนาวุฒิเข้าพบคณะกรรมการ เพื่ออธิบายข้อเท็จจริง&lt;br /&gt;
3. ครูสมทรงอธิบายเรื่องสภาพแวดล้อมได้อย่างชัดเจน ✔&lt;br /&gt;
4. นายวิชัย เขียนบันทึกข้อความ อธิบายเหตุผลการไม่เข้าร่วมประชุม&lt;br /&gt;&lt;br /&gt;


	คำอธิบาย&lt;br /&gt;&lt;br /&gt;

ชี้แจง - ขยายความให้เข้าใจชัดเจน เช่น ชี้แจงข้อกล่าวหา ชี้แจงเหตุผล ชี้แจงข้อเท็จจริง&lt;br /&gt;&lt;br /&gt;

ข้อ 1, 2 และ 4 ควรใช้คำว่า ชี้แจง&lt;br /&gt;&lt;br /&gt;

คำตอบที่ถูก คือ ข้อ 3 &lt;br /&gt;


	</explanation>
    <isExplain>disable answer</isExplain>
    <!-- ไม่แสดงป้าย คำอธิบาย ให้คลิก  - none -->
    <!-- แสดงป้าย คำอธิบาย ให้คลิก มีเฉลย+คำอธิบาย  - yes  -->
    <!-- แสดงป้าย คำอธิบาย ให้คลิก มีเฉลย+ไม่มีคำอธิบาย  - premium only  -->
    <!-- แสดงป้าย คำอธิบาย ให้คลิก ไม่เฉลย+ไม่มีคำอธิบาย  - disable answer  -->
  </thisQuestion>
  <!-- XX -->
  <thisQuestion>
    <qNum>id01529:date1627453500</qNum>
    <question>&lt;strong&gt;คำสั่ง: &lt;/strong&gt;ให้ท่านเลือกคำตอบที่ถูกต้องที่สุด&lt;br /&gt; &lt;br /&gt;
ข้อใดใช้คำถูกต้อง&lt;br /&gt;

	</question>
    <choice_A>อย่าทำอะไรแช่มช้า เดี๋ยวจะไม่ทันการ</choice_A>
    <choice_B>เธอเยื้องกรายอย่างเชื่องช้า แลดูงามสง่ายิ่งนัก</choice_B>
    <choice_C>งูหลามตัวเขื่อง เลื้อยไปมาอย่างเชื่องช้า</choice_C>
    <choice_D>สุภาษิตโบราณว่า แช่มช้าได้พร้าสองเล่มงาม</choice_D>
    <choice_E>
    </choice_E>
    <correctAns>4</correctAns>
    <!-- A=2, B=3, C=4, D=5 -->
    <explanation>&lt;strong&gt;คำสั่ง: &lt;/strong&gt;ให้ท่านเลือกคำตอบที่ถูกต้องที่สุด&lt;br /&gt; &lt;br /&gt;

ข้อใดใช้คำถูกต้อง&lt;br /&gt;

1. อย่าทำอะไรแช่มช้า เดี๋ยวจะไม่ทันการ&lt;br /&gt;
2. เธอเยื้องกรายอย่างเชื่องช้า แลดูงามสง่ายิ่งนัก&lt;br /&gt;
3. งูหลามตัวเขื่อง เลื้อยไปมาอย่างเชื่องช้า ✔&lt;br /&gt;
4. สุภาษิตโบราณว่า แช่มช้าได้พร้าสองเล่มงาม&lt;br /&gt;&lt;br /&gt;

	คำอธิบาย&lt;br /&gt;&lt;br /&gt;

แช่มช้า - ช้า ๆ อย่างมีจังหวะ และดูงาม&lt;br /&gt;
เชื่องช้า - ไม่ว่องไว&lt;br /&gt;&lt;br /&gt;

ข้อ 1 ควรใช้ว่า เชื่องช้า&lt;br /&gt;
ข้อ 2 ควรใช้ว่า แช่มช้า&lt;br /&gt;
ข้อ 3 ถูกต้องแล้ว&lt;br /&gt;
ข้อ 4 สุภาษิตโบราณคือ ช้า ๆ ได้พร้าเล่มงาม หรือ ช้า ๆ ได้พร้าสองเล่มงาม&lt;br /&gt;&lt;br /&gt;

คำตอบที่ถูก คือ ข้อ 3 &lt;br /&gt;


	</explanation>
    <isExplain>disable answer</isExplain>
    <!-- ไม่แสดงป้าย คำอธิบาย ให้คลิก  - none -->
    <!-- แสดงป้าย คำอธิบาย ให้คลิก มีเฉลย+คำอธิบาย  - yes  -->
    <!-- แสดงป้าย คำอธิบาย ให้คลิก มีเฉลย+ไม่มีคำอธิบาย  - premium only  -->
    <!-- แสดงป้าย คำอธิบาย ให้คลิก ไม่เฉลย+ไม่มีคำอธิบาย  - disable answer  -->
  </thisQuestion>
  <!-- XX -->
  <thisQuestion>
    <qNum>id01530:date1627453500</qNum>
    <question>&lt;strong&gt;คำสั่ง: &lt;/strong&gt;ให้ท่านเลือกคำตอบที่ถูกต้องที่สุด&lt;br /&gt; &lt;br /&gt;
ข้อใดใช้คำถูกต้อง&lt;br /&gt;

	</question>
    <choice_A>แม่ครัวเฉือนหนังปลาออกจากเนื้อ</choice_A>
    <choice_B>เขาหั่นมะเขือเทศเป็นแว่นๆ</choice_B>
    <choice_C>พ่อครัวฝานเปลือกมะม่วง อย่างชำนาญ</choice_C>
    <choice_D> เขาเจียนใบตองให้เป็นฝอย</choice_D>
    <choice_E>
    </choice_E>
    <correctAns>3</correctAns>
    <!-- A=2, B=3, C=4, D=5 -->
    <explanation>&lt;strong&gt;คำสั่ง: &lt;/strong&gt;ให้ท่านเลือกคำตอบที่ถูกต้องที่สุด&lt;br /&gt; &lt;br /&gt;

ข้อใดใช้คำถูกต้อง&lt;br /&gt;&lt;br /&gt;

1. แม่ครัวเฉือนหนังปลาออกจากเนื้อ&lt;br /&gt;
2. เขาหั่นมะเขือเทศเป็นแว่น ๆ ✔&lt;br /&gt;
3. พ่อครัวฝานเปลือกมะม่วง อย่างชำนาญ&lt;br /&gt;
4. เขาเจียนใบตองออกจากกัน เป็นสองส่วน&lt;br /&gt;&lt;br /&gt; 

	คำอธิบาย&lt;br /&gt;&lt;br /&gt;

ข้อ 1. ควรใช้คำว่า "แล่.png&quot;&gt;&lt;br /&gt;
แล่ - นอนใบมีดแล้วเฉือนเอาออก เช่น แล่เอาแต่เนื้อ ๆ&lt;br /&gt;&lt;br /&gt;

ข้อ 2. การหั่นของออกเป็นแว่น ๆ เป็นชิ้น ๆ ควรใช้คำว่า "หั่น.png&quot;&gt;&lt;br /&gt;&lt;br /&gt;

ข้อ 3. ควรใช้คำว่า "ปอก" &lt;br /&gt;
ปอก - เอาเปลือกหรือสิ่งที่ห่อหุ้มออก&lt;br /&gt;&lt;br /&gt;

ข้อ 4. ควรใช้คำว่า "ฉีก.png&quot;&gt;&lt;br /&gt;
ฉีก - ขาดแยกออกจากกันหรือทำให้ขาดหรือแยกออกจากกัน&lt;br /&gt;
เจียน - ตัด ขริบ หรือเฉือนให้ไปตามแนวหรือให้ได้รูปตามที่ต้องการ&lt;br /&gt;&lt;br /&gt;

คำตอบที่ถูก คือ ข้อ 2 &lt;br /&gt;


	</explanation>
    <isExplain>disable answer</isExplain>
    <!-- ไม่แสดงป้าย คำอธิบาย ให้คลิก  - none -->
    <!-- แสดงป้าย คำอธิบาย ให้คลิก มีเฉลย+คำอธิบาย  - yes  -->
    <!-- แสดงป้าย คำอธิบาย ให้คลิก มีเฉลย+ไม่มีคำอธิบาย  - premium only  -->
    <!-- แสดงป้าย คำอธิบาย ให้คลิก ไม่เฉลย+ไม่มีคำอธิบาย  - disable answer  -->
  </thisQuestion>
  <!-- XX -->
  <thisQuestion>
    <qNum>id01531:date1627453500</qNum>
    <question>&lt;strong&gt;คำสั่ง: &lt;/strong&gt;ให้ท่านเลือกคำตอบที่ถูกต้องที่สุด&lt;br /&gt; &lt;br /&gt;
ข้อใดใช้คำถูกต้อง&lt;br /&gt;

	</question>
    <choice_A>การแสดงวันนี้เป็นลิเกประสมโรง เพราะผู้เล่นมาจากต่างคณะกัน</choice_A>
    <choice_B>เขาพยายามอธิบายเรื่องที่เกิดขึ้นให้เจ้าหน้าที่รับทราบ</choice_B>
    <choice_C>ครูกำลังชี้แจงเรื่องการเกิดสุริยุปราคาเต็มดวง</choice_C>
    <choice_D>ชีวิตนักเขียนของเขากำลังโชติช่วงถึงขีดสุด</choice_D>
    <choice_E>
    </choice_E>
    <correctAns>2</correctAns>
    <!-- A=2, B=3, C=4, D=5 -->
    <explanation>&lt;strong&gt;คำสั่ง: &lt;/strong&gt;ให้ท่านเลือกคำตอบที่ถูกต้องที่สุด&lt;br /&gt; &lt;br /&gt;

ข้อใดใช้คำถูกต้อง&lt;br /&gt;&lt;br /&gt;

1. การแสดงวันนี้เป็นลิเกประสมโรง เพราะผู้เล่นมาจากต่างคณะกัน ✔&lt;br /&gt;
2. เขาพยายามอธิบายเรื่องที่เกิดขึ้นให้เจ้าหน้าที่รับทราบ &lt;br /&gt;
3. ครูกำลังชี้แจงเรื่องการเกิดสุริยุปราคาเต็มดวง &lt;br /&gt;
4. ชีวิตนักเขียนของเขากำลังโชติช่วงถึงขีดสุด &lt;br /&gt;&lt;br /&gt;


	คำอธิบาย&lt;br /&gt;&lt;br /&gt;

ข้อ 1 ถูกต้องแล้ว &lt;br /&gt;
ประสม - รวมกันเข้า (เป็นคำใช้ได้ทั่ว ๆ ไป) &lt;br /&gt;
ประสมโรง - เอาคนที่เป็นลิเกหรือละครเป็นต้นต่างโรงมาเล่นรวมกัน&lt;br /&gt;&lt;br /&gt;

ข้อ 2 ควรใช้ว่า ชี้แจงให้ทราบ&lt;br /&gt;
ชี้แจง - พูดขยายความให้เข้าใจชัดเจน&lt;br /&gt;&lt;br /&gt;

ข้อ 3 ควรใช้คำว่า อธิบาย&lt;br /&gt;
อธิบาย - ไขความ, ขยายความ, ชี้แจง  &lt;br /&gt;&lt;br /&gt;

ข้อ 4 ควรใช้คำว่า รุ่งโรจน์ (เจริญรุ่งเรือง)&lt;br /&gt;
รุ่งโรจน์ - กระจ่างแจ้ง, โชติช่วง, เช่น แสงไฟรุ่งโรจน์, เจริญรุ่งเรือง เช่น ชีวิตรุ่งโรจน์ &lt;br /&gt;
โชติช่วง -. สว่างรุ่งโรจน์, ช่วงโชติ ก็ว่า เช่น ไฟลุกสว่างโชติช่วง&lt;br /&gt;&lt;br /&gt;

คำตอบที่ถูก คือ ข้อ 1 &lt;br /&gt;


	</explanation>
    <isExplain>disable answer</isExplain>
    <!-- ไม่แสดงป้าย คำอธิบาย ให้คลิก  - none -->
    <!-- แสดงป้าย คำอธิบาย ให้คลิก มีเฉลย+คำอธิบาย  - yes  -->
    <!-- แสดงป้าย คำอธิบาย ให้คลิก มีเฉลย+ไม่มีคำอธิบาย  - premium only  -->
    <!-- แสดงป้าย คำอธิบาย ให้คลิก ไม่เฉลย+ไม่มีคำอธิบาย  - disable answer  -->
  </thisQuestion>
  <!-- XX -->
  <thisQuestion>
    <qNum>id01532:date1627453500</qNum>
    <question>&lt;strong&gt;คำสั่ง: &lt;/strong&gt;ให้ท่านเลือกคำตอบที่ถูกต้องที่สุด&lt;br /&gt; &lt;br /&gt;
ข้อใดใช้คำถูกต้อง&lt;br /&gt;

	</question>
    <choice_A>คณะกรรมการอธิบายข้อเท็จจริง กรณีนักเรียนเตรียมทหารเสียชีวิต</choice_A>
    <choice_B>สองคนนี้เหมือนขนมพอสมน้ำยา ต่างคนต่างคุยโม้ ว่าตัวเองเก่ง</choice_B>
    <choice_C>เด็ก ๆ วิ่งเล่นกัน จนเหงื่อโทรมตัว</choice_C>
    <choice_D>วัยรุ่นที่รุมโซมผู้หญิง ถูกศาลสั่งประหารชีวิตทุกคน</choice_D>
    <choice_E>
    </choice_E>
    <correctAns>3</correctAns>
    <!-- A=2, B=3, C=4, D=5 -->
    <explanation>&lt;strong&gt;คำสั่ง: &lt;/strong&gt;ให้ท่านเลือกคำตอบที่ถูกต้องที่สุด&lt;br /&gt; &lt;br /&gt;

ข้อใดใช้คำถูกต้อง&lt;br /&gt;&lt;br /&gt;

1. คณะกรรมการอธิบายข้อเท็จจริง กรณีนักเรียนเตรียมทหารเสียชีวิต&lt;br /&gt;
2. สองคนนี้เหมือนขนมพอสมน้ำยา ต่างคนต่างคุยโม้ ว่าตัวเองเก่ง&lt;br /&gt;
3. เด็ก ๆ วิ่งเล่นกัน จนเหงื่อโทรมตัว&lt;br /&gt;
4. วัยรุ่นที่รุมโซมผู้หญิง ถูกศาลสั่งประหารชีวิตทุกคน&lt;br /&gt;&lt;br /&gt;


	คำอธิบาย&lt;br /&gt;&lt;br /&gt;

ข้อ 1 ควรใช้คำว่า ชี้แจง&lt;br /&gt;&lt;br /&gt;

ข้อ 2 ถูกแล้ว&lt;br /&gt;
ขนมพอสมน้ำยา หรือ ขนมผสมน้ำยา ก็ได้ &lt;br /&gt;
ขนมผสมน้ำยา - พอดีกัน จะว่าข้างไหนดีกว่ากันไม่ได้ &lt;br /&gt;&lt;br /&gt;

ข้อ 3 คำที่ถูกคือ เหงื่อโซมตัว&lt;br /&gt;
โซม - เปียกทั่ว เช่น เหงื่อโซมตัว&lt;br /&gt;
โทรม - เสื่อมสภาพเดิม เช่น เรือนหลังนี้โทรมมาก ปีนี้เธอดูโทรมลงไปมาก&lt;br /&gt;&lt;br /&gt;

ข้อ 4 คำที่ถูกคือ โทรมหญิง&lt;br /&gt;&lt;br /&gt;

คำตอบที่ถูก คือ ข้อ  &lt;br /&gt;


	</explanation>
    <isExplain>disable answer</isExplain>
    <!-- ไม่แสดงป้าย คำอธิบาย ให้คลิก  - none -->
    <!-- แสดงป้าย คำอธิบาย ให้คลิก มีเฉลย+คำอธิบาย  - yes  -->
    <!-- แสดงป้าย คำอธิบาย ให้คลิก มีเฉลย+ไม่มีคำอธิบาย  - premium only  -->
    <!-- แสดงป้าย คำอธิบาย ให้คลิก ไม่เฉลย+ไม่มีคำอธิบาย  - disable answer  -->
  </thisQuestion>
  <!-- XX -->
  <thisQuestion>
    <qNum>id01533:date1627453500</qNum>
    <question>&lt;strong&gt;คำสั่ง: &lt;/strong&gt;ให้ท่านเลือกคำตอบที่ถูกต้องที่สุด&lt;br /&gt; &lt;br /&gt;
ข้อใดใช้คำถูกต้อง&lt;br /&gt;

	</question>
    <choice_A>แต่งงานผิด ก็เลิกกันได้ จะไปทนเซ้าซี้อยู่ทำไม</choice_A>
    <choice_B>คุณไม่ต้องมาทู่ซี้เลยนะ อย่างไรฉันก็ไม่ช่วย</choice_B>
    <choice_C>ครูสมสิทธิ์ทำเรื่องขอเบิกเงินค่าตอบแทนทำงานล่วงเวลา</choice_C>
    <choice_D>เมื่อลูกจ้างประสบอุบัติเหตุจากการทำงาน จะได้รับเงินตอบแทนจากสำนักงานประกันสังคม</choice_D>
    <choice_E>
    </choice_E>
    <correctAns>4</correctAns>
    <!-- A=2, B=3, C=4, D=5 -->
    <explanation>&lt;strong&gt;คำสั่ง: &lt;/strong&gt;ให้ท่านเลือกคำตอบที่ถูกต้องที่สุด&lt;br /&gt; &lt;br /&gt;
ข้อใดใช้คำถูกต้อง&lt;br /&gt;&lt;br /&gt;

1. แต่งงานผิด ก็เลิกกันได้ จะไปทนเซ้าซี้อยู่ทำไม&lt;br /&gt;
2. คุณไม่ต้องมาทู่ซี้เลยนะ อย่างไรฉันก็ไม่ช่วย&lt;br /&gt;
3. ครูสมสิทธิ์ทำเรื่องขอเบิกเงินค่าตอบแทนทำงานล่วงเวลา  ✔&lt;br /&gt;
4. เมื่อลูกจ้างประสบอุบัติเหตุจากการทำงาน จะได้รับเงินตอบแทนจากสำนักงานประกันสังคม&lt;br /&gt;&lt;br /&gt;


	คำอธิบาย&lt;br /&gt;&lt;br /&gt;

ทู่ซี้ - ทนไปจนกว่าจะตาย, ทนไปเพราะความจำเป็นหรือเพื่อให้สมประสงค์ &lt;br /&gt;&lt;br /&gt;

เซ้าซี้ - พูดรบเร้ารํ่าไรเพื่อให้ได้ตามที่ต้องการ&lt;br /&gt;&lt;br /&gt;

ค่าตอบแทน คือ ค่าใช้จ่ายต่าง ๆ ที่องค์การจ่ายให้แก่ผู้ปฏิบัติงาน เพื่อตอบแทนการปฏิบัติงานตามหน้าที่ความรับผิดชอบ จูงใจให้มีการปฏิบัติงานอย่างมีประสิทธิภาพส่งเสริมขวัญกำลังใจของผู้ปฏิบัติงาน และเสริมสร้างฐานะ ความเป็นอยู่ของครอบครัว ผู้ปฏิบัติงานให้ดขึ้น ทำงานล่วงเวลา จะได้รับเงินค่าตอบแทน&lt;br /&gt;&lt;br /&gt;

เงินทดแทนให้แก่ลูกจ้าง คือเงินที่สำนักงานประกันสังคม จ่ายให้ลูกจ้าง เมื่อลูกจ้างประสบอันตรายหรือเจ็บป่วย หรือถึงแก่ความตาย หรือสูญหาย เนื่องจากการทำงานให้นายจ้าง&lt;br /&gt;&lt;br /&gt;

ข้อ 1 ต้องใช้คำว่า ทู่ซี้&lt;br /&gt;&lt;br /&gt;ี้

ข้อ 2 ต้องใช้คำว่า เซ้าซี้ &lt;br /&gt;&lt;br /&gt;

ข้อ 3 ถูกต้อง&lt;br /&gt;&lt;br /&gt;

ข้อ 4 ต้องใช้คำว่า เงินทดแทน&lt;br /&gt;&lt;br /&gt;

คำตอบที่ถูก คือ ข้อ 3 &lt;br /&gt;&lt;br /&gt;
ขอบคุณ Remilia Scarlet ที่ช่วยตรวจสอบข้อนี้ &lt;br /&gt;

	</explanation>
    <isExplain>disable answer</isExplain>
    <!-- ไม่แสดงป้าย คำอธิบาย ให้คลิก  - none -->
    <!-- แสดงป้าย คำอธิบาย ให้คลิก มีเฉลย+คำอธิบาย  - yes  -->
    <!-- แสดงป้าย คำอธิบาย ให้คลิก มีเฉลย+ไม่มีคำอธิบาย  - premium only  -->
    <!-- แสดงป้าย คำอธิบาย ให้คลิก ไม่เฉลย+ไม่มีคำอธิบาย  - disable answer  -->
  </thisQuestion>
  <!-- XX -->
  <thisQuestion>
    <qNum>id01534:date1627453500</qNum>
    <question>&lt;strong&gt;คำสั่ง: &lt;/strong&gt;ให้ท่านเลือกคำตอบที่ถูกต้องที่สุด&lt;br /&gt; &lt;br /&gt;
ข้อใดใช้คำถูกต้อง&lt;br /&gt;

	</question>
    <choice_A>วันขึ้นปีใหม่ เราควรประดับธงชาติ และตบแต่งบ้านเรือนให้สวยงาม</choice_A>
    <choice_B>สมภพคิดไว้ว่า ปีนี้จะตกแต่งลูกสาวให้เป็นฝั่งเป็นฝาเสียที</choice_B>
    <choice_C>ก่อนออกจากบ้าน ควรตรวจสอบว่าปิดน้ำ ปิดไฟเรียบร้อยดีหรือไม่</choice_C>
    <choice_D>สุนทร ได้รับการแต่งตั้งให้เป็น คณะกรรมการ ตรวจตราการทุจริต การขายข้าว</choice_D>
    <choice_E>
    </choice_E>
    <correctAns>2</correctAns>
    <!-- A=2, B=3, C=4, D=5 -->
    <explanation>&lt;strong&gt;คำสั่ง: &lt;/strong&gt;ให้ท่านเลือกคำตอบที่ถูกต้องที่สุด&lt;br /&gt; &lt;br /&gt;

ข้อใดใช้คำถูกต้อง&lt;br /&gt;

1. วันขึ้นปีใหม่ เราควรประดับธงชาติ และตบแต่งบ้านเรือนให้สวยงาม ✔&lt;br /&gt;
2. สมภพคิดไว้ว่า ปีนี้จะตกแต่งลูกสาวให้เป็นฝั่งเป็นฝาเสียที &lt;br /&gt;
3. ก่อนออกจากบ้าน ควรตรวจสอบว่าปิดน้ำ ปิดไฟเรียบร้อยดีหรือไม่ &lt;br /&gt;
4. สุนทร ได้รับการแต่งตั้งให้เป็น คณะกรรมการ ตรวจตราการทุจริต การขายข้าว &lt;br /&gt; &lt;br /&gt;


	คำอธิบาย&lt;br /&gt;&lt;br /&gt;

ตกแต่ง - ประดับ, ปรุงจัดให้ดี, ทำให้งาม, เช่น ของตกแต่งบ้าน, ตบแต่ง ก็ว่า. &lt;br /&gt; &lt;br /&gt;

ตบแต่ง(1) - ประดับ, ปรุงจัดให้ดี, ทำให้งาม, เช่น ของตบแต่งบ้าน, ตกแต่ง ก็ว่า. &lt;br /&gt; &lt;br /&gt;

ตบแต่ง(2) - จัดให้ลูกสาวมีเรือนตามประเพณี เช่น ตบแต่งลูกสาวให้เป็นฝั่งเป็นฝา &lt;br /&gt; &lt;br /&gt;

ตรวจตรา - พิจารณาดูให้รอบคอบถี่ถ้วน &lt;br /&gt; &lt;br /&gt;

ตรวจสอบ - ตรวจเพื่อค้นหาข้อเท็จจริง เช่น ตำรวจไปตรวจสอบหาหลักฐานในสถานที่เกิดเหตุ  &lt;br /&gt; &lt;br /&gt;

ข้อ 1 ถูกต้องแล้ว ตบแต่ง ในข้อนี้ มีความหมายเดียวกับคำว่า ตกแต่ง คือ ประดับ จัดให้ดี  &lt;br /&gt; &lt;br /&gt;

ข้อ 2 คำที่ถูกคือ ตกแต่งลูกสาว &lt;br /&gt; &lt;br /&gt;

ข้อ 3 คำที่ถูกคือ ตรวจตรา คือ ดูให้รอบคอบ &lt;br /&gt; &lt;br /&gt;

ข้อ 4 คำที่ถูกคือ ตรวจสอบ เพราะต้องมีการสืบสวน หาพยานหลักฐานต่าง ๆ จะใช้ตรวจตรา ไม่ได้  &lt;br /&gt; &lt;br /&gt;

คำตอบที่ถูก คือ ข้อ 1 &lt;br /&gt;


	</explanation>
    <isExplain>disable answer</isExplain>
    <!-- ไม่แสดงป้าย คำอธิบาย ให้คลิก  - none -->
    <!-- แสดงป้าย คำอธิบาย ให้คลิก มีเฉลย+คำอธิบาย  - yes  -->
    <!-- แสดงป้าย คำอธิบาย ให้คลิก มีเฉลย+ไม่มีคำอธิบาย  - premium only  -->
    <!-- แสดงป้าย คำอธิบาย ให้คลิก ไม่เฉลย+ไม่มีคำอธิบาย  - disable answer  -->
  </thisQuestion>
  <!-- ถึงตรงนี้ -->
  <!-- กำลังเอามาจากหนังสือ คำที่มีความหมายใกล้เคียงกัน หน้า 82-->
  <!-- XX -->
  <thisQuestion>
    <qNum>id01535:date1627453500</qNum>
    <question>&lt;strong&gt;คำสั่ง: &lt;/strong&gt;ให้ท่านเลือกคำตอบที่ถูกต้องที่สุด&lt;br /&gt; &lt;br /&gt;
ข้อใดใช้คำถูกต้อง&lt;br /&gt;

	</question>
    <choice_A>ทั้งสองฝ่ายโต้ตอบกันด้วยคำพูดอย่างเผ็ดร้อน เข้าทำนอง ขิงก็ราข่าก็แรง</choice_A>
    <choice_B>ถึงแม้เขาจะทำอะไรให้เจ็บใจมาก ก็ให้เฉยไว้ ไม่ต้องโต้ตอบ</choice_B>
    <choice_C>UN ประกาศตอบโต้เกาหลีเหนือทดสอบนิวเคลียร์.</choice_C>
    <choice_D>มัวแต่เขียนหนังสือตอบโต้กันไปมาอย่างนี้ เมื่อไรจะได้ข้อยุติ</choice_D>
    <choice_E>
    </choice_E>
    <correctAns>4</correctAns>
    <!-- A=2, B=3, C=4, D=5 -->
    <explanation>&lt;strong&gt;คำสั่ง: &lt;/strong&gt;ให้ท่านเลือกคำตอบที่ถูกต้องที่สุด&lt;br /&gt; &lt;br /&gt;

ข้อใดใช้คำถูกต้อง&lt;br /&gt;&lt;br /&gt;

1. ทั้งสองฝ่ายโต้ตอบกันด้วยคำพูดอย่างเผ็ดร้อน เข้าทำนอง ขิงก็ราข่าก็แรง &lt;br /&gt;
2. ถึงแม้เขาจะทำอะไรให้เจ็บใจมาก ก็ให้เฉยไว้ ไม่ต้องโต้ตอบ &lt;br /&gt;
3. UN ประกาศตอบโต้เกาหลีเหนือทดสอบนิวเคลียร์ ✔&lt;br /&gt;
4. มัวแต่เขียนหนังสือตอบโต้กันไปมาอย่างนี้ เมื่อไรจะได้ข้อยุติ &lt;br /&gt;

	คำอธิบาย&lt;br /&gt;&lt;br /&gt;


ตอบโต้ - โต้กลับไป, ตอบแทนการกระทำของฝ่ายตรงข้าม, แก้แค้น&lt;br /&gt;&lt;br /&gt;

โต้ตอบ - มีหนังสือไปมา, ตอบกันไปมาในเรื่องนั้น ๆ&lt;br /&gt;&lt;br /&gt;

ข้อ 1 ควรใช้คำว่า ตอบโต้ &lt;br /&gt;&lt;br /&gt;

ข้อ 2 ควรใช้คำว่า ตอบโต้ &lt;br /&gt;&lt;br /&gt;

ข้อ 3 ถูกต้องแล้ว &lt;br /&gt;&lt;br /&gt;

ข้อ 4 ควรใช้คำว่า โต้ตอบ&lt;br /&gt;&lt;br /&gt;


คำตอบที่ถูก คือ ข้อ  &lt;br /&gt;
&lt;br /&gt;ขอบคุณ Remilia Scarlet ที่ช่วยตรวจสอบข้อนี้  &lt;br /&gt;

	</explanation>
    <isExplain>disable answer</isExplain>
    <!-- ไม่แสดงป้าย คำอธิบาย ให้คลิก  - none -->
    <!-- แสดงป้าย คำอธิบาย ให้คลิก มีเฉลย+คำอธิบาย  - yes  -->
    <!-- แสดงป้าย คำอธิบาย ให้คลิก มีเฉลย+ไม่มีคำอธิบาย  - premium only  -->
    <!-- แสดงป้าย คำอธิบาย ให้คลิก ไม่เฉลย+ไม่มีคำอธิบาย  - disable answer  -->
  </thisQuestion>
  <!-- XX -->
  <thisQuestion>
    <qNum>id01536:date1627453500</qNum>
    <question>&lt;strong&gt;คำสั่ง: &lt;/strong&gt;ให้ท่านเลือกคำตอบที่ถูกต้องที่สุด&lt;br /&gt; &lt;br /&gt;
ข้อใดใช้คำถูกต้อง&lt;br /&gt;

	</question>
    <choice_A>ทหารทั้งสองฝ่าย ต่างยิงโต้ตอบกันอย่างหูดับตับไหม้</choice_A>
    <choice_B>มีการเจรจาเพื่อสันติภาพตอบโต้กันอย่างมีเหตุผลน่าฟังทั้งสองผ่าย</choice_B>
    <choice_C>ได้ฟังการโต้ตอบกัน ระหว่างสุดาและมาลี แล้วรู้สึกนึกขำ</choice_C>
    <choice_D>ปรีชาเขียนจดหมายตอบโต้ข้อสงสัยของปรานี</choice_D>
    <choice_E>
    </choice_E>
    <correctAns>4</correctAns>
    <!-- A=2, B=3, C=4, D=5 -->
    <explanation>&lt;strong&gt;คำสั่ง: &lt;/strong&gt;ให้ท่านเลือกคำตอบที่ถูกต้องที่สุด&lt;br /&gt; &lt;br /&gt;

ข้อใดใช้คำถูกต้อง&lt;br /&gt;&lt;br /&gt;

1. ทหารทั้งสองฝ่าย ต่างยิงโต้ตอบกันอย่างหูดับตับไหม้ &lt;br /&gt;
 2. มีการเจรจาเพื่อสันติภาพตอบโต้กันอย่างมีเหตุผลน่าฟังทั้งสองผ่าย&lt;br /&gt;
3. ได้ฟังการโต้ตอบกัน ระหว่างสุดาและมาลี แล้วรู้สึกนึกขำ ✔&lt;br /&gt;
4. ปรีชาเขียนจดหมายตอบโต้ข้อสงสัยของปรานี &lt;br /&gt;&lt;br /&gt;


	คำอธิบาย&lt;br /&gt;&lt;br /&gt;

ตอบโต้ - โต้กลับไป, ตอบแทนการกระทำของฝ่ายตรงข้าม, แก้แค้น&lt;br /&gt;&lt;br /&gt;

โต้ตอบ - มีหนังสือไปมา, ตอบกันไปมาในเรื่องนั้น ๆ&lt;br /&gt;&lt;br /&gt;

ข้อ 1 ควรใช้คำว่า ตอบโต้ - ยิงตอบโต้ &lt;br /&gt;&lt;br /&gt;

ข้อ 2 ควรใช้คำว่า โต้ตอบ - เจรจาโต้ตอบ &lt;br /&gt;&lt;br /&gt;

ข้อ 3 ถูกต้องแล้ว &lt;br /&gt;&lt;br /&gt;

ข้อ 4 ควรใช้คำว่า ชี้แจง&lt;br /&gt;&lt;br /&gt;


คำตอบที่ถูก คือ ข้อ 3 &lt;br /&gt;


	</explanation>
    <isExplain>disable answer</isExplain>
    <!-- ไม่แสดงป้าย คำอธิบาย ให้คลิก  - none -->
    <!-- แสดงป้าย คำอธิบาย ให้คลิก มีเฉลย+คำอธิบาย  - yes  -->
    <!-- แสดงป้าย คำอธิบาย ให้คลิก มีเฉลย+ไม่มีคำอธิบาย  - premium only  -->
    <!-- แสดงป้าย คำอธิบาย ให้คลิก ไม่เฉลย+ไม่มีคำอธิบาย  - disable answer  -->
  </thisQuestion>
  <!-- XX -->
  <thisQuestion>
    <qNum>id01537:date1627453500</qNum>
    <question>&lt;strong&gt;คำสั่ง: &lt;/strong&gt;ให้ท่านเลือกคำตอบที่ถูกต้องที่สุด&lt;br /&gt; &lt;br /&gt;
ข้อใดใช้คำถูกต้อง&lt;br /&gt;

	</question>
    <choice_A>เขาตายใจว่าสอบผ่านแน่นอน จึงไม่ค่อยอ่านหนังสือ</choice_A>
    <choice_B>เขาหลอกให้เธอนอนใจ ก่อนที่จะเชิดเงินหนี</choice_B>
    <choice_C>มัวตายใจอยได้ ไม่รีบไป เดี๋ยวไปไม่ทันงานนะ</choice_C>
    <choice_D>ฉันตายใจนึกว่าเขาเป็นคนดี แต่ที่แท้เป็นโจรชัด ๆ</choice_D>
    <choice_E>
    </choice_E>
    <correctAns>5</correctAns>
    <!-- A=2, B=3, C=4, D=5 -->
    <explanation>&lt;strong&gt;คำสั่ง: &lt;/strong&gt;ให้ท่านเลือกคำตอบที่ถูกต้องที่สุด&lt;br /&gt; &lt;br /&gt;
ข้อใดใช้คำถูกต้อง&lt;br /&gt;&lt;br /&gt;

1. เขาตายใจว่าสอบผ่านแน่นอน จึงไม่ค่อยอ่านหนังสือ&lt;br /&gt;
2. เขาหลอกให้เธอนอนใจ ก่อนที่จะเชิดเงินหนี&lt;br /&gt;
3. มัวตายใจอยู่ได้ ไม่รีบไป เดี๋ยวไปไม่ทันงานนะ&lt;br /&gt;
4. ฉันตายใจนึกว่าเขาเป็นคนดี แต่ที่แท้เป็นโจรชัด ๆ ✔&lt;br /&gt;&lt;br /&gt;


	คำอธิบาย&lt;br /&gt;&lt;br /&gt;

นอนใจ - วางใจ, ไม่รีบร้อน&lt;br /&gt;
ตายใจ - หลงเชื่ออย่างไม่สงสัย&lt;br /&gt;&lt;br /&gt;

ข้อ 1 ควรใช้คำว่า นอนใจ&lt;br /&gt;&lt;br /&gt;

ข้อ 2 ควรใช้คำว่า ตายใจ&lt;br /&gt;&lt;br /&gt;

ข้อ 3 ควรใช้คำว่า นอนใจ&lt;br /&gt;&lt;br /&gt;

ข้อ 4 ถูกต้องแล้ว&lt;br /&gt;&lt;br /&gt;

คำตอบที่ถูก คือ ข้อ.4  &lt;br /&gt;


	</explanation>
    <isExplain>disable answer</isExplain>
    <!-- ไม่แสดงป้าย คำอธิบาย ให้คลิก  - none -->
    <!-- แสดงป้าย คำอธิบาย ให้คลิก มีเฉลย+คำอธิบาย  - yes  -->
    <!-- แสดงป้าย คำอธิบาย ให้คลิก มีเฉลย+ไม่มีคำอธิบาย  - premium only  -->
    <!-- แสดงป้าย คำอธิบาย ให้คลิก ไม่เฉลย+ไม่มีคำอธิบาย  - disable answer  -->
  </thisQuestion>
  <!-- XX -->
  <thisQuestion>
    <qNum>id01538:date1627453500</qNum>
    <question>&lt;strong&gt;คำสั่ง: &lt;/strong&gt;ให้ท่านเลือกคำตอบที่ถูกต้องที่สุด&lt;br /&gt; &lt;br /&gt;
ข้อใดใช้คำถูกต้อง&lt;br /&gt;

	</question>
    <choice_A>ประเทศที่เกี่ยวข้องระหว่างกรณีพิพาทนี้มีหลายประเทศ</choice_A>
    <choice_B>แผนงานที่เสนอขึ้นมานี้สอดคล้องแก่เจตนาของคณะกรรมการ</choice_B>
    <choice_C>นักพูดที่ดีต้องรู้จักเลือกใช้ถ้อยคำให้เหมาะสมแก่ผู้ฟ้งและโอกาส</choice_C>
    <choice_D>นักศึกษาที่ลงทะเบียนช้ากว่ากำหนด ต้องยื่นคำร้องกับเจ้าหน้าที่ ก่อนสิ้นเดือนกุมภาพันธ</choice_D>
    <choice_E>
    </choice_E>
    <correctAns>4</correctAns>
    <!-- A=2, B=3, C=4, D=5 -->
    <explanation>&lt;strong&gt;คำสั่ง: &lt;/strong&gt;ให้ท่านเลือกคำตอบที่ถูกต้องที่สุด&lt;br /&gt; &lt;br /&gt;
ข้อใดใช้คำถูกต้อง&lt;br /&gt;&lt;br /&gt;

1. ประเทศที่เกี่ยวข้องระหว่างกรณีพิพาทนี้มีหลายประเทศ&lt;br /&gt;
2. แผนงานที่เสนอขึ้นมานี้สอดคล้องแก่เจตนาของคณะกรรมการ&lt;br /&gt;
3. นักพูดที่ดีต้องรู้จักเลือกใช้ถ้อยคำให้เหมาะสมแก่ผู้ฟ้งและโอกาส ✔ &lt;br /&gt;
4. นักศึกษาที่ลงทะเบียนช้ากว่ากำหนด ต้องยื่นคำร้องกับเจ้าหน้าที่ ก่อนสิ้นเดือนกุมภาพันธ์ &lt;br /&gt;

	คำอธิบาย&lt;br /&gt;&lt;br /&gt;

ข้อ 1. ควรใช้คำว่า กับ - เกี่ยวข้องกับกรณีพิพาท &lt;br /&gt;
ข้อ 2. ควรใช้คำว่า กับ - สอดคล้องกับเจตนา&lt;br /&gt;
ข้อ 3. ถูกต้องแล้ว&lt;br /&gt;
ข้อ 4. ควรใช้คำว่า ต่อ&lt;br /&gt;&lt;br /&gt;

กับ เป็นคำที่เชื่อมคำหรือความเข้าด้วยกัน มีความหมายว่า รวมกันหรือเกี่ยวข้องกัน เช่น ฟ้ากับดิน กินกับนอน หายวับไปกับตา&lt;br /&gt;&lt;br /&gt;

แก่ - ใช้นำหน้านามฝ่ายรัก เช่น ให้เงินแก่เด็ก&lt;br /&gt;&lt;br /&gt;

แต่ - นำหน้านามบอกเวลาหรือบอกสถานที่ เช่น มาแต่เช้า มาแต่บ้าน แต่ไหนแต่ไรมา&lt;br /&gt;&lt;br /&gt;

แด่ - แก่ (ใช้ในที่เคารพ)&lt;br /&gt;&lt;br /&gt;

ต่อ - เรียกสิ่งที่เชื่อมเข้าด้วยกัน เช่น คำต่อ (คือคำบุรพบทและคำสันธาน) ข้อต่อ บ.เฉพาะ, ประจันหน้า, เช่น ต่อหน้า ยื่นต่ออำเภอ&lt;br /&gt;&lt;br /&gt;

คำตอบที่ถูก คือ ข้อ 3 &lt;br /&gt;


	</explanation>
    <isExplain>disable answer</isExplain>
    <!-- ไม่แสดงป้าย คำอธิบาย ให้คลิก  - none -->
    <!-- แสดงป้าย คำอธิบาย ให้คลิก มีเฉลย+คำอธิบาย  - yes  -->
    <!-- แสดงป้าย คำอธิบาย ให้คลิก มีเฉลย+ไม่มีคำอธิบาย  - premium only  -->
    <!-- แสดงป้าย คำอธิบาย ให้คลิก ไม่เฉลย+ไม่มีคำอธิบาย  - disable answer  -->
  </thisQuestion>
  <!-- XX -->
  <thisQuestion>
    <qNum>id01539:date1627453500</qNum>
    <question>&lt;strong&gt;คำสั่ง: &lt;/strong&gt;ให้ท่านเลือกคำตอบที่ถูกต้องที่สุด&lt;br /&gt; &lt;br /&gt;
ข้อใดใช้ฟุ่มเฟือย&lt;br /&gt;

	</question>
    <choice_A>สถานตากอากาศแห่งนี้ เป็นที่รู้จักและเป็นที่นิยม ของคนจำนวนมาก</choice_A>
    <choice_B>เขารู้สึกละอายใจมากที่ทุจริตคดโกงในการสอบ</choice_B>
    <choice_C>ความเครียดนับวันจะเป็นสาเหต ุให้เกิดปัญหาสังคมถึงขั้นวิกฤต</choice_C>
    <choice_D>ปัญหาสุขภาพจิตเป็นผลจากความเครียดทั้งร่างกายและจิตใจ</choice_D>
    <choice_E>
    </choice_E>
    <correctAns>3</correctAns>
    <!-- A=2, B=3, C=4, D=5 -->
    <explanation>&lt;strong&gt;คำสั่ง: &lt;/strong&gt;ให้ท่านเลือกคำตอบที่ถูกต้องที่สุด&lt;br /&gt; &lt;br /&gt;
ข้อใดใช้ฟุ่มเฟือย&lt;br /&gt;&lt;br /&gt;

1. สถานตากอากาศแห่งนี้ เป็นที่รู้จักและเป็นที่นิยม ของคนจำนวนมาก&lt;br /&gt;
2. เขารู้สึกละอายใจมากที่ทุจริตคดโกงในการสอบ ✔&lt;br /&gt;
3. ความเครียดนับวันจะเป็นสาเหตุให้เกิดปัญหาสังคม ถึงขั้นวิกฤต&lt;br /&gt;
4. ปัญหาสุขภาพจิต เป็นผลจากความเครียดทั้งร่างกายและจิตใจ&lt;br /&gt;&lt;br /&gt;

	คำอธิบาย&lt;br /&gt;&lt;br /&gt;

ข้อ 2. มีการใช้คำฟุ่มเฟือย คำว่า ทุจริตกับคดโกง มีความหมายที่คล้ายกัน เราสามารถตัดคำใดคำหนึ่ง ออกไปได้ โดยประโยคยังคงความหมายเช่นเดิม&lt;br /&gt;


คำตอบที่ถูก คือ ข้อ 2 &lt;br /&gt;


	</explanation>
    <isExplain>disable answer</isExplain>
    <!-- ไม่แสดงป้าย คำอธิบาย ให้คลิก  - none -->
    <!-- แสดงป้าย คำอธิบาย ให้คลิก มีเฉลย+คำอธิบาย  - yes  -->
    <!-- แสดงป้าย คำอธิบาย ให้คลิก มีเฉลย+ไม่มีคำอธิบาย  - premium only  -->
    <!-- แสดงป้าย คำอธิบาย ให้คลิก ไม่เฉลย+ไม่มีคำอธิบาย  - disable answer  -->
  </thisQuestion>
  <!-- XX -->
  <thisQuestion>
    <qNum>id01540:date1627453500</qNum>
    <question>&lt;strong&gt;คำสั่ง: &lt;/strong&gt;ให้ท่านเลือกคำตอบที่ถูกต้องที่สุด&lt;br /&gt; &lt;br /&gt;
ข้อใดใช้ภาษาเหมาะสมที่สุด&lt;br /&gt;

	</question>
    <choice_A>พ่อแม่อยากให้ฉันเป็นหมอ แต่ฉันอยากเป็นครูบ้านนอก</choice_A>
    <choice_B>มารดาของข้าพเจ้าเสียชีวิตตั้งแต่ข้าพเจ้ายังเล็ก ๆ คุณพ่อจึงมี ภรรยาใหม่</choice_B>
    <choice_C>คุณพ่อคุณแม่ทั้งหลาย ต่างต้องการให้บุตรธิดาของตนประสบความสำเร็จในชีวิต</choice_C>
    <choice_D>หนังสือเล่มนี้มีหวังขายได้เกลี้ยงเพราะรวบรวมวาทะสำคัญ ๆ ของผู้ที่มีชื่อเสียงหลายคน</choice_D>
    <choice_E>
    </choice_E>
    <correctAns>2</correctAns>
    <!-- A=2, B=3, C=4, D=5 -->
    <explanation>&lt;strong&gt;คำสั่ง: &lt;/strong&gt;ให้ท่านเลือกคำตอบที่ถูกต้องที่สุด&lt;br /&gt; &lt;br /&gt;
ข้อใดใช้ภาษาเหมาะสมที่สุด&lt;br /&gt;&lt;br /&gt;

1. พ่อแม่อยากให้ฉันเป็นหมอ แต่ฉันอยากเป็นครูบ้านนอก ✔&lt;br /&gt;
2. มารดาของข้าพเจ้าเสียชีวิตตั้งแต่ข้าพเจ้ายังเล็ก ๆ คุณพ่อจึงมี ภรรยาใหม่&lt;br /&gt;
3. คุณพ่อคุณแม่ทั้งหลาย ต่างต้องการให้บุตรธิดาของตนประสบความสำเร็จในชีวิต&lt;br /&gt;
4. หนังสือเล่มนี้มีหวังขายได้เกลี้ยงเพราะรวบรวมวาทะสำคัญ ๆ ของผู้ที่มีชื่อเสียงหลายคน&lt;br /&gt;&lt;br /&gt;

	คำอธิบาย&lt;br /&gt;&lt;br /&gt;

ข้อ 1. ถูกต้อง ใช้คำระดับเดียวกัน พ่อ-แม่-หมอ-ฉัน-ครู &lt;br /&gt;&lt;br /&gt;

ข้อ 2. ใช้คำต่างระดับกัน มารดา-ข้าพเจ้า-คุณพ่อ(ควรเป็น บิดา)&lt;br /&gt;&lt;br /&gt;

ข้อ 3. ใช้คำต่างระดับกัน คุณพ่อ-คุณแม่-บุตรธิดา (ควรเป็น ลูก ๆ)&lt;br /&gt;&lt;br /&gt;

ข้อ 4. คำว่า "มีหวังขายได้เกลี้ยง" ไม่ใช่ภาษาเขียน ควรเป็น คาดว่าจะจำหน่ายได้หมด&lt;br /&gt;&lt;br /&gt;

คำตอบที่ถูก คือ ข้อ 1  &lt;br /&gt;


	</explanation>
    <isExplain>disable answer</isExplain>
    <!-- ไม่แสดงป้าย คำอธิบาย ให้คลิก  - none -->
    <!-- แสดงป้าย คำอธิบาย ให้คลิก มีเฉลย+คำอธิบาย  - yes  -->
    <!-- แสดงป้าย คำอธิบาย ให้คลิก มีเฉลย+ไม่มีคำอธิบาย  - premium only  -->
    <!-- แสดงป้าย คำอธิบาย ให้คลิก ไม่เฉลย+ไม่มีคำอธิบาย  - disable answer  -->
  </thisQuestion>
  <!-- XX -->
  <thisQuestion>
    <qNum>id01541:date1627453500</qNum>
    <question>&lt;strong&gt;คำสั่ง: &lt;/strong&gt;ให้ท่านเลือกคำตอบที่ถูกต้องที่สุด&lt;br /&gt; &lt;br /&gt;
ประโยคในข้อใด ถูกต้องที่สุด&lt;br /&gt;

	</question>
    <choice_A>พรานป่าล่าช้างเพื่อเอางาอย่างอำมหิต</choice_A>
    <choice_B>เขาไม่ได้ต่อสู้ตามที่ประกาศไว้ อย่างสมศักดิ์ศรี</choice_B>
    <choice_C>การพูดโน้มน้าว แม้ไม่มีหลักฐานประกอบที่มีเหตุผล ก็พอจะเชื่อได้</choice_C>
    <choice_D>อาจารย์อนุญาตให้นักเรียนทำรายงานทางวิชาการตามโครงร่าง ที่เสนอมา</choice_D>
    <choice_E>
    </choice_E>
    <correctAns>5</correctAns>
    <!-- A=2, B=3, C=4, D=5 -->
    <explanation>&lt;strong&gt;คำสั่ง: &lt;/strong&gt;ให้ท่านเลือกคำตอบที่ถูกต้องที่สุด&lt;br /&gt; &lt;br /&gt;
ประโยคในข้อใด ถูกต้องที่สุด&lt;br /&gt;&lt;br /&gt;

1. พรานป่าล่าช้างเพื่อเอางาอย่างอำมหิต&lt;br /&gt;
2. เขาไม่ได้ต่อสู้ตามที่ประกาศไว้ อย่างสมศักดิ์ศรี &lt;br /&gt;
3. การพูดโน้มน้าว แม้ไม่มีหลักฐานประกอบที่มีเหตุผล ก็พอจะเชื่อได้ &lt;br /&gt;
4. อาจารย์อนุญาตให้นักเรียนทำรายงานทางวิชาการตามโครงร่าง ที่เสนอมา ✔&lt;br /&gt;&lt;br /&gt;

	คำอธิบาย&lt;br /&gt;&lt;br /&gt;

ข้อ 1. ควรพูดว่า พรานป่าล่าช้างอย่างอำมหิต เพื่อเอางา&lt;br /&gt;&lt;br /&gt;

ข้อ 2. ควรพูดว่า เขาไม่ได้ต่อสู้อย่างสมศักดิ์ศรี ตามที่ประกาศไว้ &lt;br /&gt;&lt;br /&gt;

ข้อ 3. ควรพูดว่า การพูดโน้มน้าวที่มีเหตุผล แม้ไม่มีหลักฐานประกอบ ก็พอจะเชื่อได้ &lt;br /&gt;&lt;br /&gt;

ข้อ 4. วางคำขยายถูกต้องแล้ว&lt;br /&gt;&lt;br /&gt;

คำตอบที่ถูก คือ ข้อ 4 &lt;br /&gt;


	</explanation>
    <isExplain>disable answer</isExplain>
    <!-- ไม่แสดงป้าย คำอธิบาย ให้คลิก  - none -->
    <!-- แสดงป้าย คำอธิบาย ให้คลิก มีเฉลย+คำอธิบาย  - yes  -->
    <!-- แสดงป้าย คำอธิบาย ให้คลิก มีเฉลย+ไม่มีคำอธิบาย  - premium only  -->
    <!-- แสดงป้าย คำอธิบาย ให้คลิก ไม่เฉลย+ไม่มีคำอธิบาย  - disable answer  -->
  </thisQuestion>
  <!-- XX -->
  <thisQuestion>
    <qNum>id01542:date1627453500</qNum>
    <question>&lt;strong&gt;คำสั่ง: &lt;/strong&gt;ให้ท่านเลือกคำตอบที่ถูกต้องที่สุด&lt;br /&gt; &lt;br /&gt;
ข้อใดเรียงลำดับคำได้เหมาะสมที่สุด&lt;br /&gt;

	</question>
    <choice_A>เมื่อถึงฤดูสารท ในประเทศอินเดีย มีคดิถือกันว่าผู้มีอาชีพกสิกรรม จะเก็บพืชพันธ์ธัญญาหาร ที่ออกผลครั้งแรก ไปทำขนมสำหรับไหว้ บรรพบุรุษที่ล่วงลับไปแล้ว</choice_A>
    <choice_B>มีคติถือกันว่า เมื่อถึงฤดูสารทในประเทศอินเดีย ผู้ที่มีอาชีพกสิกรรม จะเก็บพืชพันธ์ธัญญาหารที่ออกผลครั้งแรก ไปทำขนมสำหรับ ไหว้บรรพบุรุษที่ล่วลับไปแล้ว</choice_B>
    <choice_C>ในประเทศอินเดีย มีคติถือกันว่า เมื่อถึงฤดูสารท ผู้มีอาชีพกสิกรรม จะเก็บพืชพันธ์ธัญญาหาร ที่ออกผลครั้งแรก ไปทำขนมสำหรับ ไหว้บรรพบุรุษที่ล่วงลับไปแล้ว</choice_C>
    <choice_D>ผู้ที่มีอาชีพกสิกรรม มีคติถือกันว่า เมื่อถึงฤดูสารท ในประเทศอินเดีย จะเก็บพืชพันธ์ธัญญาหาร ที่ออกผลครั้งแรกไปทำขนม สำหรับไหว้บรรพบุรุษที่ล่วงกับไปแล้ว</choice_D>
    <choice_E>
    </choice_E>
    <correctAns>4</correctAns>
    <!-- A=2, B=3, C=4, D=5 -->
    <explanation>&lt;strong&gt;คำสั่ง: &lt;/strong&gt;ให้ท่านเลือกคำตอบที่ถูกต้องที่สุด&lt;br /&gt; &lt;br /&gt;

ข้อใดเรียงลำดับคำได้เหมาะสมที่สุด&lt;br /&gt;&lt;br /&gt;

1. เมื่อถึงฤดูสารท ในประเทศอินเดีย มีคดิถือกันว่าผู้มีอาชีพกสิกรรม จะเก็บพืชพันธ์ธัญญาหาร ที่ออกผลครั้งแรก ไปทำขนมสำหรับไหว้ บรรพบุรุษที่ล่วงลับไปแล้ว&lt;br /&gt;
2. มีคติถือกันว่า เมื่อถึงฤดูสารทในประเทศอินเดีย ผู้ที่มีอาชีพกสิกรรม จะเก็บพืชพันธ์ธัญญาหารที่ออกผลครั้งแรก ไปทำขนมสำหรับ ไหว้บรรพบุรุษที่ล่วลับไปแล้ว&lt;br /&gt;
3. ในประเทศอินเดีย มีคติถือกันว่า เมื่อถึงฤดูสารท ผู้มีอาชีพกสิกรรม จะเก็บพืชพันธ์ธัญญาหาร ที่ออกผลครั้งแรก ไปทำขนมสำหรับ ไหว้บรรพบุรุษที่ล่วงลับไปแล้ว ✔&lt;br /&gt;
4. ผู้ที่มีอาชีพกสิกรรม มีคติถือกันว่า เมื่อถึงฤดูสารท ในประเทศอินเดีย จะเก็บพืชพันธ์ธัญญาหาร ที่ออกผลครั้งแรกไปทำขนม สำหรับไหว้บรรพบุรุษที่ล่วงกับไปแล้ว&lt;br /&gt;&lt;br /&gt;

	คำอธิบาย&lt;br /&gt;&lt;br /&gt;

ข้อ 3 ถูกต้องที่สุด เพราะ คำว่า "ในประเทศอินเดีย" เป็นกรอบความคิดที่กว้างที่สุด ในข้อความเหล่านี้ จึงควรกล่าวเน้นครั้งแรก&lt;br /&gt;&lt;br /&gt;


คำตอบที่ถูก คือ ข้อ 3  &lt;br /&gt;


	</explanation>
    <isExplain>disable answer</isExplain>
    <!-- ไม่แสดงป้าย คำอธิบาย ให้คลิก  - none -->
    <!-- แสดงป้าย คำอธิบาย ให้คลิก มีเฉลย+คำอธิบาย  - yes  -->
    <!-- แสดงป้าย คำอธิบาย ให้คลิก มีเฉลย+ไม่มีคำอธิบาย  - premium only  -->
    <!-- แสดงป้าย คำอธิบาย ให้คลิก ไม่เฉลย+ไม่มีคำอธิบาย  - disable answer  -->
  </thisQuestion>
</exams>


